[{"id": "4890", "name": "AARTH", "segment": "SME", "_pg": 1, "n_issues": 50.0, "avg_listing_gain": 27.21, "avg_current_gain": 36.83, "total_inv_cr": 101.23}, {"id": "3349", "name": "VIKASA", "segment": "SME", "_pg": 1, "n_issues": 53.0, "avg_listing_gain": 23.44, "avg_current_gain": 40.03, "total_inv_cr": 98.57}, {"id": "4852", "name": "RAJASTHAN GLOBAL SECURITIES", "segment": "SME", "_pg": 1, "n_issues": 61.0, "avg_listing_gain": 23.54, "avg_current_gain": 29.63, "total_inv_cr": 94.81}, {"id": "2756", "name": "SAINT CAPITAL", "segment": "SME", "_pg": 1, "n_issues": 44.0, "avg_listing_gain": 22.21, "avg_current_gain": 21.65, "total_inv_cr": 89.65}, {"id": "798", "name": "CRAFT EMERGING MARKET FUND PCC", "segment": "SME", "_pg": 1, "n_issues": 24.0, "avg_listing_gain": 9.31, "avg_current_gain": 28.94, "total_inv_cr": 80.8}, {"id": "4341", "name": "SANSHI", "segment": "SME", "_pg": 2, "n_issues": 18.0, "avg_listing_gain": 29.88, "avg_current_gain": 106.55, "total_inv_cr": 73.39}, {"id": "4848", "name": "LRSD SECURITIES", "segment": "SME", "_pg": 2, "n_issues": 19.0, "avg_listing_gain": 18.25, "avg_current_gain": 30.01, "total_inv_cr": 65.92}, {"id": "3843", "name": "FINAVENUE", "segment": "SME", "_pg": 2, "n_issues": 33.0, "avg_listing_gain": 30.43, "avg_current_gain": 78.03, "total_inv_cr": 62.64}, {"id": "4871", "name": "NAV CAPITAL", "segment": "SME", "_pg": 2, "n_issues": 31.0, "avg_listing_gain": 22.91, "avg_current_gain": 41.74, "total_inv_cr": 62.25}, {"id": "2119", "name": "MINT FOCUSED", "segment": "SME", "_pg": 2, "n_issues": 22.0, "avg_listing_gain": 24.07, "avg_current_gain": 30.57, "total_inv_cr": 55.1}, {"id": "4883", "name": "BHARAT VENTURE", "segment": "SME", "_pg": 3, "n_issues": 14.0, "avg_listing_gain": 35.79, "avg_current_gain": 97.26, "total_inv_cr": 54.24}, {"id": "4888", "name": "VINEY", "segment": "SME", "_pg": 3, "n_issues": 33.0, "avg_listing_gain": 22.82, "avg_current_gain": 4.57, "total_inv_cr": 53.14}, {"id": "2075", "name": "MERU INVESTMENT", "segment": "SME", "_pg": 3, "n_issues": 24.0, "avg_listing_gain": 28.28, "avg_current_gain": 35.77, "total_inv_cr": 49.58}, {"id": "1560", "name": "INDIA MAX INVESTMENT FUND LTD.", "segment": "SME", "_pg": 3, "n_issues": 14.0, "avg_listing_gain": 24.44, "avg_current_gain": 95.78, "total_inv_cr": 46.63}, {"id": "2481", "name": "PINE OAK", "segment": "SME", "_pg": 3, "n_issues": 14.0, "avg_listing_gain": 25.08, "avg_current_gain": 58.86, "total_inv_cr": 45.64}, {"id": "4882", "name": "BEACON STONE CAPITAL", "segment": "SME", "_pg": 4, "n_issues": 20.0, "avg_listing_gain": 22.59, "avg_current_gain": 22.62, "total_inv_cr": 43.82}, {"id": "4018", "name": "INVICTA", "segment": "SME", "_pg": 4, "n_issues": 13.0, "avg_listing_gain": 28.02, "avg_current_gain": 29.84, "total_inv_cr": 38.89}, {"id": "4876", "name": "SB OPPORTUNITIES FUND", "segment": "SME", "_pg": 4, "n_issues": 30.0, "avg_listing_gain": 24.51, "avg_current_gain": 43.83, "total_inv_cr": 36.86}, {"id": "121", "name": "ABUNDANTIA", "segment": "SME", "_pg": 4, "n_issues": 13.0, "avg_listing_gain": 23.15, "avg_current_gain": 1.96, "total_inv_cr": 34.37}, {"id": "4173", "name": "NEGEN", "segment": "SME", "_pg": 4, "n_issues": 11.0, "avg_listing_gain": 8.18, "avg_current_gain": 4.87, "total_inv_cr": 34.15}, {"id": "4853", "name": "SHINE STAR", "segment": "SME", "_pg": 5, "n_issues": 20.0, "avg_listing_gain": 26.98, "avg_current_gain": 49.6, "total_inv_cr": 32.21}, {"id": "4007", "name": "INNOVATIVE VISION", "segment": "SME", "_pg": 5, "n_issues": 19.0, "avg_listing_gain": 21.61, "avg_current_gain": 3.34, "total_inv_cr": 32.03}, {"id": "4444", "name": "SUNRISE", "segment": "SME", "_pg": 5, "n_issues": 22.0, "avg_listing_gain": 14.3, "avg_current_gain": 16.09, "total_inv_cr": 30.08}, {"id": "1041", "name": "EMINENCE", "segment": "SME", "_pg": 5, "n_issues": 13.0, "avg_listing_gain": 9.67, "avg_current_gain": 43.05, "total_inv_cr": 28.21}, {"id": "4565", "name": "WEALTHWAVE", "segment": "SME", "_pg": 5, "n_issues": 4.0, "avg_listing_gain": 7.15, "avg_current_gain": 84.4, "total_inv_cr": 27.6}, {"id": "4858", "name": "BENGAL FINANCE & INVESTMENT", "segment": "SME", "_pg": 6, "n_issues": 4.0, "avg_listing_gain": 31.67, "avg_current_gain": 44.02, "total_inv_cr": 25.51}, {"id": "4187", "name": "NINE ALPS", "segment": "SME", "_pg": 6, "n_issues": 9.0, "avg_listing_gain": 35.9, "avg_current_gain": 54.41, "total_inv_cr": 24.68}, {"id": "4850", "name": "MONEYWISE FINANCIAL SERVICES", "segment": "SME", "_pg": 6, "n_issues": 16.0, "avg_listing_gain": 16.63, "avg_current_gain": -4.87, "total_inv_cr": 24.23}, {"id": "1543", "name": "INDIA CAPITAL", "segment": "SME", "_pg": 6, "n_issues": 9.0, "avg_listing_gain": 19.73, "avg_current_gain": 56.26, "total_inv_cr": 23.14}, {"id": "4128", "name": "MAVIRA", "segment": "SME", "_pg": 6, "n_issues": 9.0, "avg_listing_gain": 25.07, "avg_current_gain": 35.33, "total_inv_cr": 22.88}, {"id": "2301", "name": "NORTH STAR", "segment": "SME", "_pg": 7, "n_issues": 9.0, "avg_listing_gain": 30.59, "avg_current_gain": 70.51, "total_inv_cr": 22.4}, {"id": "2263", "name": "NEXUS", "segment": "SME", "_pg": 7, "n_issues": 15.0, "avg_listing_gain": 5.96, "avg_current_gain": 4.57, "total_inv_cr": 21.63}, {"id": "2233", "name": "NECTA BLOOM VCC", "segment": "SME", "_pg": 7, "n_issues": 9.0, "avg_listing_gain": 41.96, "avg_current_gain": 8.22, "total_inv_cr": 20.67}, {"id": "4881", "name": "ZEAL GLOBAL", "segment": "SME", "_pg": 7, "n_issues": 12.0, "avg_listing_gain": 11.58, "avg_current_gain": 21.23, "total_inv_cr": 20.24}, {"id": "4840", "name": "STRATEGIC SIXTH SENSE", "segment": "SME", "_pg": 7, "n_issues": 14.0, "avg_listing_gain": 8.27, "avg_current_gain": 2.36, "total_inv_cr": 19.28}, {"id": "4866", "name": "FOUNDERS COLLECTIVE FUND", "segment": "SME", "_pg": 8, "n_issues": 3.0, "avg_listing_gain": 16.01, "avg_current_gain": 124.81, "total_inv_cr": 19.22}, {"id": "4428", "name": "STEPTRADE", "segment": "SME", "_pg": 8, "n_issues": 16.0, "avg_listing_gain": 20.41, "avg_current_gain": -2.51, "total_inv_cr": 18.96}, {"id": "4249", "name": "PERSISTENT", "segment": "SME", "_pg": 8, "n_issues": 11.0, "avg_listing_gain": 24.49, "avg_current_gain": 25.48, "total_inv_cr": 18.55}, {"id": "2116", "name": "MINERVA", "segment": "SME", "_pg": 8, "n_issues": 11.0, "avg_listing_gain": 26.31, "avg_current_gain": 97.3, "total_inv_cr": 17.12}, {"id": "4182", "name": "NEXT ORBIT", "segment": "SME", "_pg": 8, "n_issues": 10.0, "avg_listing_gain": 11.75, "avg_current_gain": 6.01, "total_inv_cr": 16.38}, {"id": "4194", "name": "NIVESHAAY", "segment": "SME", "_pg": 9, "n_issues": 5.0, "avg_listing_gain": 2.02, "avg_current_gain": -4.43, "total_inv_cr": 15.92}, {"id": "1619", "name": "INTI CAPITAL", "segment": "SME", "_pg": 9, "n_issues": 5.0, "avg_listing_gain": 19.21, "avg_current_gain": 31.73, "total_inv_cr": 15.82}, {"id": "4861", "name": "JALAN CHEMICAL INDUSTRIES", "segment": "SME", "_pg": 9, "n_issues": 12.0, "avg_listing_gain": 17.52, "avg_current_gain": 47.31, "total_inv_cr": 15.82}, {"id": "3862", "name": "FORTUNE HANDS", "segment": "SME", "_pg": 9, "n_issues": 8.0, "avg_listing_gain": 26.67, "avg_current_gain": 49.27, "total_inv_cr": 15.75}, {"id": "4857", "name": "ASHIKA GLOBAL SECURITIES", "segment": "SME", "_pg": 9, "n_issues": 13.0, "avg_listing_gain": 8.57, "avg_current_gain": -10.95, "total_inv_cr": 15.62}, {"id": "669", "name": "CHANAKYA", "segment": "SME", "_pg": 10, "n_issues": 9.0, "avg_listing_gain": 15.91, "avg_current_gain": 57.0, "total_inv_cr": 15.59}, {"id": "4860", "name": "FINVESTA FIRST", "segment": "SME", "_pg": 10, "n_issues": 11.0, "avg_listing_gain": 10.86, "avg_current_gain": 17.47, "total_inv_cr": 15.34}, {"id": "4141", "name": "MILI", "segment": "SME", "_pg": 10, "n_issues": 14.0, "avg_listing_gain": 13.3, "avg_current_gain": -1.48, "total_inv_cr": 15.18}, {"id": "3491", "name": "ZETA GLOBAL FUNDS (OEIC) PCC LTD.", "segment": "SME", "_pg": 10, "n_issues": 9.0, "avg_listing_gain": 14.48, "avg_current_gain": 24.49, "total_inv_cr": 15.16}, {"id": "3714", "name": "CCV", "segment": "SME", "_pg": 10, "n_issues": 8.0, "avg_listing_gain": 10.76, "avg_current_gain": 30.78, "total_inv_cr": 15.14}, {"id": "4535", "name": "VELOCE", "segment": "SME", "_pg": 11, "n_issues": 7.0, "avg_listing_gain": 0.36, "avg_current_gain": -36.95, "total_inv_cr": 14.62}, {"id": "2312", "name": "NOVA", "segment": "SME", "_pg": 11, "n_issues": 8.0, "avg_listing_gain": 17.34, "avg_current_gain": 19.78, "total_inv_cr": 14.43}, {"id": "4886", "name": "HDFC BANK", "segment": "SME", "_pg": 11, "n_issues": 12.0, "avg_listing_gain": 36.0, "avg_current_gain": 37.66, "total_inv_cr": 14.12}, {"id": "3507", "name": "31 DEGREES", "segment": "SME", "_pg": 11, "n_issues": 8.0, "avg_listing_gain": 13.36, "avg_current_gain": 15.37, "total_inv_cr": 13.28}, {"id": "4884", "name": "COMPACT STRUCTURE FUND", "segment": "SME", "_pg": 11, "n_issues": 6.0, "avg_listing_gain": 0.46, "avg_current_gain": -21.16, "total_inv_cr": 12.99}, {"id": "1940", "name": "M7 GLOBAL", "segment": "SME", "_pg": 12, "n_issues": 8.0, "avg_listing_gain": 15.33, "avg_current_gain": 13.52, "total_inv_cr": 12.87}, {"id": "4898", "name": "HOLANI VENTURE", "segment": "SME", "_pg": 12, "n_issues": 7.0, "avg_listing_gain": 43.62, "avg_current_gain": 11.41, "total_inv_cr": 12.77}, {"id": "4859", "name": "CHHATTISGARH INVESTMENTS", "segment": "SME", "_pg": 12, "n_issues": 9.0, "avg_listing_gain": 9.76, "avg_current_gain": 22.27, "total_inv_cr": 12.5}, {"id": "2897", "name": "SILVER STRIDE", "segment": "SME", "_pg": 12, "n_issues": 7.0, "avg_listing_gain": 24.53, "avg_current_gain": 8.64, "total_inv_cr": 12.42}, {"id": "3917", "name": "HOLANI", "segment": "SME", "_pg": 12, "n_issues": 8.0, "avg_listing_gain": 4.54, "avg_current_gain": -0.46, "total_inv_cr": 12.41}, {"id": "4396", "name": "SMART HORIZON", "segment": "SME", "_pg": 13, "n_issues": 12.0, "avg_listing_gain": 19.89, "avg_current_gain": 15.07, "total_inv_cr": 12.26}, {"id": "47", "name": "WHITEOAK CAPITAL MUTUAL FUND", "segment": "SME", "_pg": 13, "n_issues": 2.0, "avg_listing_gain": 9.65, "avg_current_gain": -49.0, "total_inv_cr": 12.22}, {"id": "2652", "name": "RADIANT GLOBAL", "segment": "SME", "_pg": 13, "n_issues": 7.0, "avg_listing_gain": 27.91, "avg_current_gain": 20.16, "total_inv_cr": 12.12}, {"id": "343", "name": "ARNESTA", "segment": "SME", "_pg": 13, "n_issues": 8.0, "avg_listing_gain": 8.2, "avg_current_gain": 0.63, "total_inv_cr": 12.07}, {"id": "4865", "name": "ELITE CAPITAL", "segment": "SME", "_pg": 13, "n_issues": 2.0, "avg_listing_gain": -5.37, "avg_current_gain": 93.31, "total_inv_cr": 12.01}, {"id": "4867", "name": "GROBIZ SME OPPORTUNITIES", "segment": "SME", "_pg": 14, "n_issues": 10.0, "avg_listing_gain": 8.08, "avg_current_gain": 31.3, "total_inv_cr": 11.68}, {"id": "4880", "name": "YR INVESTMENT", "segment": "SME", "_pg": 14, "n_issues": 6.0, "avg_listing_gain": 3.7, "avg_current_gain": 30.78, "total_inv_cr": 11.68}, {"id": "4461", "name": "TATTVAM", "segment": "SME", "_pg": 14, "n_issues": 8.0, "avg_listing_gain": 17.88, "avg_current_gain": 15.73, "total_inv_cr": 11.46}, {"id": "4547", "name": "VIJIT", "segment": "SME", "_pg": 14, "n_issues": 10.0, "avg_listing_gain": 21.42, "avg_current_gain": 21.91, "total_inv_cr": 11.46}, {"id": "1912", "name": "LORDS MULTIGROWTH", "segment": "SME", "_pg": 14, "n_issues": 5.0, "avg_listing_gain": 0.5, "avg_current_gain": 2.21, "total_inv_cr": 11.38}, {"id": "1795", "name": "KINGSMAN WEALTH FUND PCC", "segment": "SME", "_pg": 15, "n_issues": 8.0, "avg_listing_gain": 7.4, "avg_current_gain": 46.34, "total_inv_cr": 10.67}, {"id": "4068", "name": "KRUSHNAM NEXUS", "segment": "SME", "_pg": 15, "n_issues": 7.0, "avg_listing_gain": 3.59, "avg_current_gain": 5.23, "total_inv_cr": 10.55}, {"id": "4451", "name": "SWYOM", "segment": "SME", "_pg": 15, "n_issues": 8.0, "avg_listing_gain": 8.22, "avg_current_gain": -33.85, "total_inv_cr": 10.5}, {"id": "3739", "name": "COGNIZANT", "segment": "SME", "_pg": 15, "n_issues": 3.0, "avg_listing_gain": 58.38, "avg_current_gain": 232.8, "total_inv_cr": 9.51}, {"id": "1947", "name": "MAGNIFICA GLOBAL OPPORTUNITIES VCC", "segment": "SME", "_pg": 15, "n_issues": 4.0, "avg_listing_gain": 39.75, "avg_current_gain": 66.27, "total_inv_cr": 9.28}, {"id": "3829", "name": "EVERGROW", "segment": "SME", "_pg": 16, "n_issues": 7.0, "avg_listing_gain": 15.45, "avg_current_gain": 23.51, "total_inv_cr": 9.11}, {"id": "637", "name": "CARNELIAN", "segment": "SME", "_pg": 16, "n_issues": 2.0, "avg_listing_gain": 9.6, "avg_current_gain": 192.68, "total_inv_cr": 9.09}, {"id": "4235", "name": "PARADISE MOON", "segment": "SME", "_pg": 16, "n_issues": 9.0, "avg_listing_gain": 11.59, "avg_current_gain": -0.04, "total_inv_cr": 9.08}, {"id": "4878", "name": "SUBHKAM VENTURES", "segment": "SME", "_pg": 16, "n_issues": 2.0, "avg_listing_gain": 18.44, "avg_current_gain": -20.19, "total_inv_cr": 8.71}, {"id": "4170", "name": "NAVBHARAT", "segment": "SME", "_pg": 16, "n_issues": 7.0, "avg_listing_gain": 29.9, "avg_current_gain": 12.47, "total_inv_cr": 8.42}, {"id": "3707", "name": "CAPRI", "segment": "SME", "_pg": 17, "n_issues": 4.0, "avg_listing_gain": 15.76, "avg_current_gain": 32.88, "total_inv_cr": 8.32}, {"id": "3798", "name": "EKAMYA", "segment": "SME", "_pg": 17, "n_issues": 8.0, "avg_listing_gain": 17.12, "avg_current_gain": 10.26, "total_inv_cr": 8.1}, {"id": "4544", "name": "VENTUREX", "segment": "SME", "_pg": 17, "n_issues": 7.0, "avg_listing_gain": 10.06, "avg_current_gain": 4.68, "total_inv_cr": 8.06}, {"id": "1909", "name": "LONGTHRIVE CAPITAL VCC", "segment": "SME", "_pg": 17, "n_issues": 6.0, "avg_listing_gain": 19.46, "avg_current_gain": -2.85, "total_inv_cr": 7.59}, {"id": "4901", "name": "SAGEONE-FLAGSHI", "segment": "SME", "_pg": 17, "n_issues": 2.0, "avg_listing_gain": 77.82, "avg_current_gain": 357.54, "total_inv_cr": 7.49}, {"id": "3879", "name": "GETFIVE", "segment": "SME", "_pg": 18, "n_issues": 2.0, "avg_listing_gain": 7.57, "avg_current_gain": 74.11, "total_inv_cr": 7.09}, {"id": "198", "name": "AL MAHA INVESTMENT FUND PCC", "segment": "SME", "_pg": 18, "n_issues": 6.0, "avg_listing_gain": 3.02, "avg_current_gain": -52.3, "total_inv_cr": 7.04}, {"id": "8255", "name": "CP\u00a0CAPITAL", "segment": "SME", "_pg": 18, "n_issues": 4.0, "avg_listing_gain": 12.98, "avg_current_gain": 2.15, "total_inv_cr": 7.04}, {"id": "4305", "name": "RELIGO", "segment": "SME", "_pg": 18, "n_issues": 6.0, "avg_listing_gain": 38.4, "avg_current_gain": 90.93, "total_inv_cr": 7.02}, {"id": "784", "name": "COPTHALL", "segment": "SME", "_pg": 18, "n_issues": 1.0, "avg_listing_gain": -0.63, "avg_current_gain": -64.76, "total_inv_cr": 7.01}, {"id": "3641", "name": "AVORA", "segment": "SME", "_pg": 19, "n_issues": 5.0, "avg_listing_gain": 29.82, "avg_current_gain": 23.26, "total_inv_cr": 6.68}, {"id": "4123", "name": "MATTERHORN", "segment": "SME", "_pg": 19, "n_issues": 6.0, "avg_listing_gain": 35.85, "avg_current_gain": 101.61, "total_inv_cr": 6.52}, {"id": "7", "name": "BANDHAN MUTUAL FUND", "segment": "SME", "_pg": 19, "n_issues": 1.0, "avg_listing_gain": 16.09, "avg_current_gain": -13.49, "total_inv_cr": 6.18}, {"id": "4899", "name": "J4S VENTURE FUND", "segment": "SME", "_pg": 19, "n_issues": 5.0, "avg_listing_gain": 21.82, "avg_current_gain": -16.58, "total_inv_cr": 6.04}, {"id": "1852", "name": "LEADING LIGHT FUND VCC", "segment": "SME", "_pg": 19, "n_issues": 4.0, "avg_listing_gain": 23.1, "avg_current_gain": -55.37, "total_inv_cr": 6.03}, {"id": "183", "name": "AIDOS", "segment": "SME", "_pg": 20, "n_issues": 2.0, "avg_listing_gain": -7.85, "avg_current_gain": 6.93, "total_inv_cr": 6.02}, {"id": "4845", "name": "CHARTERED FINANCE & LEASING", "segment": "SME", "_pg": 20, "n_issues": 2.0, "avg_listing_gain": 46.51, "avg_current_gain": 170.89, "total_inv_cr": 6.02}, {"id": "3554", "name": "AKALPYA INDIA", "segment": "SME", "_pg": 20, "n_issues": 2.0, "avg_listing_gain": 63.1, "avg_current_gain": 103.83, "total_inv_cr": 6.01}, {"id": "985", "name": "EBISU GLOBAL", "segment": "SME", "_pg": 20, "n_issues": 2.0, "avg_listing_gain": 10.58, "avg_current_gain": 25.52, "total_inv_cr": 5.96}, {"id": "2691", "name": "RESONANCE OPPORTUNITIES", "segment": "SME", "_pg": 20, "n_issues": 5.0, "avg_listing_gain": 11.62, "avg_current_gain": 30.56, "total_inv_cr": 5.56}, {"id": "547", "name": "BRIDGE", "segment": "SME", "_pg": 21, "n_issues": 2.0, "avg_listing_gain": 3.7, "avg_current_gain": 73.77, "total_inv_cr": 5.55}, {"id": "3941", "name": "IMAP INDIA", "segment": "SME", "_pg": 21, "n_issues": 5.0, "avg_listing_gain": 7.48, "avg_current_gain": 3.22, "total_inv_cr": 5.25}, {"id": "4549", "name": "VIRA", "segment": "SME", "_pg": 21, "n_issues": 5.0, "avg_listing_gain": 39.05, "avg_current_gain": 103.5, "total_inv_cr": 5.22}, {"id": "3267", "name": "UNIVERSAL GOLDEN FUND", "segment": "SME", "_pg": 21, "n_issues": 2.0, "avg_listing_gain": 7.57, "avg_current_gain": 74.11, "total_inv_cr": 5.04}, {"id": "4533", "name": "VBCUBE", "segment": "SME", "_pg": 21, "n_issues": 4.0, "avg_listing_gain": 45.5, "avg_current_gain": 24.91, "total_inv_cr": 4.63}, {"id": "3319", "name": "VEDAS OPPORTUNITIES", "segment": "SME", "_pg": 22, "n_issues": 4.0, "avg_listing_gain": 20.8, "avg_current_gain": 71.03, "total_inv_cr": 4.53}, {"id": "3876", "name": "GENERATIONAL", "segment": "SME", "_pg": 22, "n_issues": 3.0, "avg_listing_gain": 1.65, "avg_current_gain": 4.4, "total_inv_cr": 4.51}, {"id": "4245", "name": "PENTATEAM", "segment": "SME", "_pg": 22, "n_issues": 3.0, "avg_listing_gain": 4.73, "avg_current_gain": 2.37, "total_inv_cr": 4.48}, {"id": "347", "name": "ARROW", "segment": "SME", "_pg": 22, "n_issues": 3.0, "avg_listing_gain": 4.3, "avg_current_gain": 83.47, "total_inv_cr": 4.41}, {"id": "4862", "name": "SANTOSH INDUSTRIES", "segment": "SME", "_pg": 22, "n_issues": 2.0, "avg_listing_gain": -0.14, "avg_current_gain": 25.38, "total_inv_cr": 4.4}, {"id": "104", "name": "ABANS", "segment": "SME", "_pg": 23, "n_issues": 1.0, "avg_listing_gain": 0.14, "avg_current_gain": 2.31, "total_inv_cr": 4.37}, {"id": "4292", "name": "RAGHUNATH CAPITAL", "segment": "SME", "_pg": 23, "n_issues": 4.0, "avg_listing_gain": 4.38, "avg_current_gain": -37.67, "total_inv_cr": 4.25}, {"id": "4863", "name": "3 SIGMA GLOBAL FUND", "segment": "SME", "_pg": 23, "n_issues": 3.0, "avg_listing_gain": 12.6, "avg_current_gain": 1.39, "total_inv_cr": 4.11}, {"id": "4312", "name": "RMS", "segment": "SME", "_pg": 23, "n_issues": 4.0, "avg_listing_gain": 36.41, "avg_current_gain": 56.34, "total_inv_cr": 4.08}, {"id": "327", "name": "ARES", "segment": "SME", "_pg": 23, "n_issues": 1.0, "avg_listing_gain": 0.48, "avg_current_gain": 109.3, "total_inv_cr": 4.05}, {"id": "8383", "name": "TIGER STRATEGIES", "segment": "SME", "_pg": 24, "n_issues": 3.0, "avg_listing_gain": 38.19, "avg_current_gain": 21.17, "total_inv_cr": 4.02}, {"id": "3612", "name": "ASCEND GLOBAL", "segment": "SME", "_pg": 24, "n_issues": 2.0, "avg_listing_gain": 10.82, "avg_current_gain": 134.85, "total_inv_cr": 4.0}, {"id": "3243", "name": "UNICO GLOBAL", "segment": "SME", "_pg": 24, "n_issues": 1.0, "avg_listing_gain": 21.9, "avg_current_gain": 21.78, "total_inv_cr": 3.97}, {"id": "4875", "name": "RADIANT GLOBAL FUND", "segment": "SME", "_pg": 24, "n_issues": 3.0, "avg_listing_gain": 13.54, "avg_current_gain": 20.0, "total_inv_cr": 3.96}, {"id": "4856", "name": "ARIAL HOLDING", "segment": "SME", "_pg": 24, "n_issues": 1.0, "avg_listing_gain": 0.48, "avg_current_gain": 109.3, "total_inv_cr": 3.59}, {"id": "4947", "name": "VISIONARY VALUE FUND", "segment": "SME", "_pg": 25, "n_issues": 3.0, "avg_listing_gain": 20.11, "avg_current_gain": -7.25, "total_inv_cr": 3.53}, {"id": "4870", "name": "MULTITUDE GROWTH", "segment": "SME", "_pg": 25, "n_issues": 2.0, "avg_listing_gain": 9.58, "avg_current_gain": 1.55, "total_inv_cr": 3.22}, {"id": "4398", "name": "SMC", "segment": "SME", "_pg": 25, "n_issues": 3.0, "avg_listing_gain": 13.39, "avg_current_gain": 47.54, "total_inv_cr": 3.13}, {"id": "506", "name": "BLUE ASTER", "segment": "SME", "_pg": 25, "n_issues": 2.0, "avg_listing_gain": 2.78, "avg_current_gain": 64.6, "total_inv_cr": 3.03}, {"id": "474", "name": "BELGRAVE", "segment": "SME", "_pg": 25, "n_issues": 2.0, "avg_listing_gain": 5.68, "avg_current_gain": -4.34, "total_inv_cr": 3.02}, {"id": "272", "name": "AMICORP", "segment": "SME", "_pg": 26, "n_issues": 2.0, "avg_listing_gain": 43.38, "avg_current_gain": 41.95, "total_inv_cr": 3.01}, {"id": "4034", "name": "J4S", "segment": "SME", "_pg": 26, "n_issues": 3.0, "avg_listing_gain": 48.1, "avg_current_gain": 216.32, "total_inv_cr": 3.01}, {"id": "4064", "name": "KNIGHTSTONE", "segment": "SME", "_pg": 26, "n_issues": 2.0, "avg_listing_gain": 14.01, "avg_current_gain": -69.36, "total_inv_cr": 3.01}, {"id": "4120", "name": "MASTERGROWTH 369", "segment": "SME", "_pg": 26, "n_issues": 3.0, "avg_listing_gain": 7.87, "avg_current_gain": -25.68, "total_inv_cr": 3.01}, {"id": "4164", "name": "NAKSHATRA", "segment": "SME", "_pg": 26, "n_issues": 2.0, "avg_listing_gain": 14.48, "avg_current_gain": 11.89, "total_inv_cr": 3.01}, {"id": "4274", "name": "PRIMARY OPPORTUNITY", "segment": "SME", "_pg": 27, "n_issues": 2.0, "avg_listing_gain": 59.45, "avg_current_gain": -20.38, "total_inv_cr": 3.0}, {"id": "4515", "name": "UPSURGE", "segment": "SME", "_pg": 27, "n_issues": 1.0, "avg_listing_gain": -1.34, "avg_current_gain": 33.94, "total_inv_cr": 2.74}, {"id": "2153", "name": "MORGAN STANLEY", "segment": "SME", "_pg": 27, "n_issues": 1.0, "avg_listing_gain": 60.08, "avg_current_gain": -9.6, "total_inv_cr": 2.51}, {"id": "4509", "name": "UNICORN", "segment": "SME", "_pg": 27, "n_issues": 2.0, "avg_listing_gain": -13.28, "avg_current_gain": -18.78, "total_inv_cr": 2.51}, {"id": "3580", "name": "ANAND RATHI", "segment": "SME", "_pg": 27, "n_issues": 1.0, "avg_listing_gain": 4.62, "avg_current_gain": -26.17, "total_inv_cr": 2.48}, {"id": "3326", "name": "VENUS INVESTMENTS", "segment": "SME", "_pg": 28, "n_issues": 2.0, "avg_listing_gain": -4.28, "avg_current_gain": 3.54, "total_inv_cr": 2.26}, {"id": "3648", "name": "B-FLY", "segment": "SME", "_pg": 28, "n_issues": 2.0, "avg_listing_gain": 7.3, "avg_current_gain": 28.52, "total_inv_cr": 2.22}, {"id": "3653", "name": "BENANI", "segment": "SME", "_pg": 28, "n_issues": 2.0, "avg_listing_gain": 50.94, "avg_current_gain": 8.66, "total_inv_cr": 2.03}, {"id": "8525", "name": "360 ONE PRIME LTD.", "segment": "SME", "_pg": 28, "n_issues": 2.0, "avg_listing_gain": 23.06, "avg_current_gain": -3.54, "total_inv_cr": 2.03}, {"id": "3578", "name": "AMRUT", "segment": "SME", "_pg": 28, "n_issues": 2.0, "avg_listing_gain": 20.59, "avg_current_gain": 29.0, "total_inv_cr": 2.02}, {"id": "4174", "name": "NEO", "segment": "SME", "_pg": 29, "n_issues": 2.0, "avg_listing_gain": -0.14, "avg_current_gain": 25.38, "total_inv_cr": 2.02}, {"id": "4841", "name": "TGISME", "segment": "SME", "_pg": 29, "n_issues": 2.0, "avg_listing_gain": 41.74, "avg_current_gain": 39.95, "total_inv_cr": 2.02}, {"id": "4873", "name": "NIVEZA INVESTMENTS", "segment": "SME", "_pg": 29, "n_issues": 1.0, "avg_listing_gain": 35.62, "avg_current_gain": 57.96, "total_inv_cr": 2.02}, {"id": "4250", "name": "PESB CAPITAL", "segment": "SME", "_pg": 29, "n_issues": 1.0, "avg_listing_gain": 31.25, "avg_current_gain": 25.0, "total_inv_cr": 2.01}, {"id": "4849", "name": "MILKY INVESTMENT & TRADING", "segment": "SME", "_pg": 29, "n_issues": 1.0, "avg_listing_gain": 23.53, "avg_current_gain": 236.97, "total_inv_cr": 2.01}, {"id": "4879", "name": "VEER QUANT", "segment": "SME", "_pg": 30, "n_issues": 2.0, "avg_listing_gain": 9.56, "avg_current_gain": -17.94, "total_inv_cr": 2.01}, {"id": "4932", "name": "INDIA EQUITY FUND", "segment": "SME", "_pg": 30, "n_issues": 1.0, "avg_listing_gain": -5.66, "avg_current_gain": 89.1, "total_inv_cr": 2.01}, {"id": "249", "name": "AMANSA", "segment": "SME", "_pg": 30, "n_issues": 1.0, "avg_listing_gain": 24.4, "avg_current_gain": 13.1, "total_inv_cr": 2.0}, {"id": "1621", "name": "INTUITIVE ALPHA", "segment": "SME", "_pg": 30, "n_issues": 1.0, "avg_listing_gain": -10.73, "avg_current_gain": -33.15, "total_inv_cr": 2.0}, {"id": "2390", "name": "OVATA", "segment": "SME", "_pg": 30, "n_issues": 1.0, "avg_listing_gain": 19.42, "avg_current_gain": 5.42, "total_inv_cr": 2.0}, {"id": "4847", "name": "KHANDELWAL FINANCE", "segment": "SME", "_pg": 31, "n_issues": 1.0, "avg_listing_gain": 35.62, "avg_current_gain": 57.96, "total_inv_cr": 2.0}, {"id": "4855", "name": "AMESTA GLOBAL", "segment": "SME", "_pg": 31, "n_issues": 1.0, "avg_listing_gain": 24.4, "avg_current_gain": 13.1, "total_inv_cr": 2.0}, {"id": "4166", "name": "NARNOLIA", "segment": "SME", "_pg": 31, "n_issues": 1.0, "avg_listing_gain": 26.0, "avg_current_gain": -16.88, "total_inv_cr": 1.96}, {"id": "3634", "name": "AUXANO", "segment": "SME", "_pg": 31, "n_issues": 1.0, "avg_listing_gain": -16.33, "avg_current_gain": -67.89, "total_inv_cr": 1.51}, {"id": "4934", "name": "MAIQ GROWTH", "segment": "SME", "_pg": 31, "n_issues": 1.0, "avg_listing_gain": 10.16, "avg_current_gain": -21.33, "total_inv_cr": 1.51}, {"id": "356", "name": "ARYABHATA", "segment": "SME", "_pg": 32, "n_issues": 1.0, "avg_listing_gain": 14.89, "avg_current_gain": 102.86, "total_inv_cr": 1.5}, {"id": "4531", "name": "VARDAN", "segment": "SME", "_pg": 32, "n_issues": 1.0, "avg_listing_gain": 9.03, "avg_current_gain": 57.01, "total_inv_cr": 1.5}, {"id": "4085", "name": "LILKIS", "segment": "SME", "_pg": 32, "n_issues": 1.0, "avg_listing_gain": -16.03, "avg_current_gain": -54.12, "total_inv_cr": 1.44}, {"id": "4113", "name": "MANIFESTED", "segment": "SME", "_pg": 32, "n_issues": 1.0, "avg_listing_gain": 10.34, "avg_current_gain": 48.31, "total_inv_cr": 1.2}, {"id": "4318", "name": "ROYAL ALPHA", "segment": "SME", "_pg": 32, "n_issues": 1.0, "avg_listing_gain": 40.59, "avg_current_gain": 35.15, "total_inv_cr": 1.15}, {"id": "2114", "name": "MILLTRUST", "segment": "SME", "_pg": 33, "n_issues": 1.0, "avg_listing_gain": 26.0, "avg_current_gain": -16.88, "total_inv_cr": 1.05}, {"id": "209", "name": "ALBULA", "segment": "SME", "_pg": 33, "n_issues": 1.0, "avg_listing_gain": 45.44, "avg_current_gain": 211.39, "total_inv_cr": 1.04}, {"id": "1244", "name": "GALAXY NOBLE", "segment": "SME", "_pg": 33, "n_issues": 1.0, "avg_listing_gain": -6.62, "avg_current_gain": -26.5, "total_inv_cr": 1.02}, {"id": "4915", "name": "VPK GLOBAL VENTURES", "segment": "SME", "_pg": 33, "n_issues": 1.0, "avg_listing_gain": 99.48, "avg_current_gain": 145.39, "total_inv_cr": 1.02}, {"id": "8409", "name": "MINTEXRX", "segment": "SME", "_pg": 33, "n_issues": 1.0, "avg_listing_gain": -6.62, "avg_current_gain": -26.5, "total_inv_cr": 1.02}, {"id": "294", "name": "ANTARA", "segment": "SME", "_pg": 34, "n_issues": 1.0, "avg_listing_gain": 1.61, "avg_current_gain": 151.39, "total_inv_cr": 1.01}, {"id": "661", "name": "CENTURY", "segment": "SME", "_pg": 34, "n_issues": 1.0, "avg_listing_gain": 0.7, "avg_current_gain": -23.08, "total_inv_cr": 1.01}, {"id": "716", "name": "CITRUS", "segment": "SME", "_pg": 34, "n_issues": 1.0, "avg_listing_gain": 16.09, "avg_current_gain": -13.49, "total_inv_cr": 1.01}, {"id": "819", "name": "CULLINAN OPPORTUNITIES FUND VCC", "segment": "SME", "_pg": 34, "n_issues": 1.0, "avg_listing_gain": 5.19, "avg_current_gain": 37.14, "total_inv_cr": 1.01}, {"id": "1192", "name": "FIVEX CAPITAL", "segment": "SME", "_pg": 34, "n_issues": 1.0, "avg_listing_gain": -4.16, "avg_current_gain": -13.48, "total_inv_cr": 1.01}, {"id": "1586", "name": "INFINITY", "segment": "SME", "_pg": 35, "n_issues": 1.0, "avg_listing_gain": 16.09, "avg_current_gain": -13.49, "total_inv_cr": 1.01}, {"id": "3588", "name": "ANUBHUTI", "segment": "SME", "_pg": 35, "n_issues": 1.0, "avg_listing_gain": -16.33, "avg_current_gain": -67.89, "total_inv_cr": 1.01}, {"id": "3630", "name": "AUGMENTA", "segment": "SME", "_pg": 35, "n_issues": 1.0, "avg_listing_gain": null, "avg_current_gain": 129.17, "total_inv_cr": 1.01}, {"id": "4247", "name": "PERPETUITY", "segment": "SME", "_pg": 35, "n_issues": 1.0, "avg_listing_gain": 5.54, "avg_current_gain": -42.22, "total_inv_cr": 1.01}, {"id": "4380", "name": "SIDBI", "segment": "SME", "_pg": 35, "n_issues": 1.0, "avg_listing_gain": 99.5, "avg_current_gain": -11.43, "total_inv_cr": 1.01}, {"id": "4550", "name": "VISIONARY", "segment": "SME", "_pg": 36, "n_issues": 1.0, "avg_listing_gain": -0.63, "avg_current_gain": -64.76, "total_inv_cr": 1.01}, {"id": "4554", "name": "VPK", "segment": "SME", "_pg": 36, "n_issues": 1.0, "avg_listing_gain": 60.08, "avg_current_gain": -9.6, "total_inv_cr": 1.01}, {"id": "4864", "name": "ASTRONE CAPITAL", "segment": "SME", "_pg": 36, "n_issues": 1.0, "avg_listing_gain": 14.89, "avg_current_gain": 102.86, "total_inv_cr": 1.01}, {"id": "4959", "name": "GOLDEN EQUITY", "segment": "SME", "_pg": 36, "n_issues": 1.0, "avg_listing_gain": -4.16, "avg_current_gain": -13.48, "total_inv_cr": 1.01}, {"id": "75", "name": "360 ONE", "segment": "SME", "_pg": 36, "n_issues": 1.0, "avg_listing_gain": 40.59, "avg_current_gain": 35.15, "total_inv_cr": 1.0}, {"id": "1876", "name": "LIGHTHOUSE", "segment": "SME", "_pg": 37, "n_issues": 1.0, "avg_listing_gain": 46.88, "avg_current_gain": -10.27, "total_inv_cr": 1.0}, {"id": "3298", "name": "VALUEQUEST", "segment": "SME", "_pg": 37, "n_issues": 1.0, "avg_listing_gain": 29.57, "avg_current_gain": -14.89, "total_inv_cr": 1.0}, {"id": "3609", "name": "ARTHASANCHAY", "segment": "SME", "_pg": 37, "n_issues": 1.0, "avg_listing_gain": 22.23, "avg_current_gain": -28.3, "total_inv_cr": 1.0}, {"id": "3616", "name": "ASHIKA", "segment": "SME", "_pg": 37, "n_issues": 1.0, "avg_listing_gain": 19.92, "avg_current_gain": -33.23, "total_inv_cr": 1.0}, {"id": "3706", "name": "CAPITAR", "segment": "SME", "_pg": 37, "n_issues": 1.0, "avg_listing_gain": -16.03, "avg_current_gain": -54.12, "total_inv_cr": 1.0}, {"id": "3779", "name": "DIVINE", "segment": "SME", "_pg": 38, "n_issues": 1.0, "avg_listing_gain": 9.03, "avg_current_gain": 57.01, "total_inv_cr": 1.0}, {"id": "4110", "name": "MAKIA", "segment": "SME", "_pg": 38, "n_issues": 1.0, "avg_listing_gain": 21.12, "avg_current_gain": 34.92, "total_inv_cr": 1.0}, {"id": "4212", "name": "OCULUS CAPITAL", "segment": "SME", "_pg": 38, "n_issues": 1.0, "avg_listing_gain": 22.23, "avg_current_gain": -28.3, "total_inv_cr": 1.0}, {"id": "4854", "name": "WINRO COMMERCIAL", "segment": "SME", "_pg": 38, "n_issues": 1.0, "avg_listing_gain": 40.59, "avg_current_gain": 35.15, "total_inv_cr": 1.0}, {"id": "4885", "name": "ELYSIAN", "segment": "SME", "_pg": 38, "n_issues": 1.0, "avg_listing_gain": -10.73, "avg_current_gain": -33.15, "total_inv_cr": 1.0}, {"id": "4910", "name": "SME GROWTH FUND SERIES ALPHA", "segment": "SME", "_pg": 39, "n_issues": 1.0, "avg_listing_gain": 2.86, "avg_current_gain": -14.66, "total_inv_cr": 1.0}, {"id": "38", "name": "SBI MUTUAL FUND", "segment": "Mainboard", "_pg": 1, "n_issues": 23.0, "avg_listing_gain": 19.41, "avg_current_gain": 53.33, "total_inv_cr": 2958.71}, {"id": "18", "name": "ICICI PRUDENTIAL MUTUAL FUND", "segment": "Mainboard", "_pg": 1, "n_issues": 33.0, "avg_listing_gain": 13.93, "avg_current_gain": 39.57, "total_inv_cr": 2447.42}, {"id": "15", "name": "HDFC MUTUAL FUND", "segment": "Mainboard", "_pg": 1, "n_issues": 32.0, "avg_listing_gain": 16.96, "avg_current_gain": 51.9, "total_inv_cr": 2426.31}, {"id": "24", "name": "KOTAK MAHINDRA MUTUAL FUND", "segment": "Mainboard", "_pg": 1, "n_issues": 28.0, "avg_listing_gain": 17.14, "avg_current_gain": 54.05, "total_inv_cr": 1910.62}, {"id": "30", "name": "NIPPON INDIA MUTUAL FUND", "segment": "Mainboard", "_pg": 1, "n_issues": 25.0, "avg_listing_gain": 16.78, "avg_current_gain": 38.8, "total_inv_cr": 1890.14}, {"id": "3", "name": "ADITYA BIRLA SUN LIFE MUTUAL FUND", "segment": "Mainboard", "_pg": 2, "n_issues": 29.0, "avg_listing_gain": 17.72, "avg_current_gain": 40.09, "total_inv_cr": 1809.28}, {"id": "1153", "name": "FIDELITY", "segment": "Mainboard", "_pg": 2, "n_issues": 15.0, "avg_listing_gain": 21.15, "avg_current_gain": 38.8, "total_inv_cr": 1503.68}, {"id": "5", "name": "AXIS MUTUAL FUND", "segment": "Mainboard", "_pg": 2, "n_issues": 28.0, "avg_listing_gain": 17.84, "avg_current_gain": 40.61, "total_inv_cr": 1435.02}, {"id": "1334", "name": "GOLDMAN SACHS", "segment": "Mainboard", "_pg": 2, "n_issues": 26.0, "avg_listing_gain": 19.93, "avg_current_gain": 49.39, "total_inv_cr": 1408.67}, {"id": "1345", "name": "GOVERNMENT PENSION FUND GLOBAL", "segment": "Mainboard", "_pg": 2, "n_issues": 18.0, "avg_listing_gain": 15.14, "avg_current_gain": 26.65, "total_inv_cr": 1339.86}, {"id": "28", "name": "MOTILAL OSWAL MUTUAL FUND", "segment": "Mainboard", "_pg": 3, "n_issues": 39.0, "avg_listing_gain": 16.09, "avg_current_gain": 38.85, "total_inv_cr": 1304.98}, {"id": "4810", "name": "LIFE INSURANCE CORP.OF INDIA", "segment": "Mainboard", "_pg": 3, "n_issues": 4.0, "avg_listing_gain": 12.86, "avg_current_gain": 16.23, "total_inv_cr": 1234.0}, {"id": "1342", "name": "GOVERNMENT OF SINGAPORE", "segment": "Mainboard", "_pg": 3, "n_issues": 11.0, "avg_listing_gain": 26.04, "avg_current_gain": 66.46, "total_inv_cr": 1164.45}, {"id": "363", "name": "ASHOKA WHITEOAK", "segment": "Mainboard", "_pg": 3, "n_issues": 22.0, "avg_listing_gain": 18.69, "avg_current_gain": 40.5, "total_inv_cr": 1138.41}, {"id": "119", "name": "ABU DHABI INVESTMENT", "segment": "Mainboard", "_pg": 3, "n_issues": 17.0, "avg_listing_gain": 21.59, "avg_current_gain": 64.82, "total_inv_cr": 1042.69}, {"id": "27", "name": "MIRAE ASSET MUTUAL FUND", "segment": "Mainboard", "_pg": 4, "n_issues": 25.0, "avg_listing_gain": 20.29, "avg_current_gain": 50.19, "total_inv_cr": 1030.05}, {"id": "2030", "name": "NOMURA", "segment": "Mainboard", "_pg": 4, "n_issues": 18.0, "avg_listing_gain": 16.18, "avg_current_gain": 43.12, "total_inv_cr": 954.94}, {"id": "282", "name": "AMUNDI", "segment": "Mainboard", "_pg": 4, "n_issues": 23.0, "avg_listing_gain": 10.78, "avg_current_gain": 26.96, "total_inv_cr": 876.93}, {"id": "41", "name": "TATA MUTUAL FUND", "segment": "Mainboard", "_pg": 4, "n_issues": 24.0, "avg_listing_gain": 19.46, "avg_current_gain": 41.46, "total_inv_cr": 872.54}, {"id": "8416", "name": "SMALLCAP WORLD FUND", "segment": "Mainboard", "_pg": 4, "n_issues": 7.0, "avg_listing_gain": 14.6, "avg_current_gain": 37.81, "total_inv_cr": 862.46}, {"id": "13", "name": "FRANKLIN TEMPLETON MUTUAL FUND", "segment": "Mainboard", "_pg": 5, "n_issues": 17.0, "avg_listing_gain": 20.5, "avg_current_gain": 48.53, "total_inv_cr": 749.2}, {"id": "502", "name": "BLACKROCK", "segment": "Mainboard", "_pg": 5, "n_issues": 9.0, "avg_listing_gain": 20.9, "avg_current_gain": 55.02, "total_inv_cr": 718.14}, {"id": "1", "name": "DSP MUTUAL FUND", "segment": "Mainboard", "_pg": 5, "n_issues": 16.0, "avg_listing_gain": 20.06, "avg_current_gain": 52.33, "total_inv_cr": 688.43}, {"id": "4828", "name": "SBI LIFE INSURANCE", "segment": "Mainboard", "_pg": 5, "n_issues": 15.0, "avg_listing_gain": 20.96, "avg_current_gain": 61.61, "total_inv_cr": 662.09}, {"id": "2924", "name": "SOCIETE GENERAL", "segment": "Mainboard", "_pg": 6, "n_issues": 41.0, "avg_listing_gain": 7.98, "avg_current_gain": 25.23, "total_inv_cr": 638.24}, {"id": "12", "name": "EDELWEISS MUTUAL FUND", "segment": "Mainboard", "_pg": 6, "n_issues": 35.0, "avg_listing_gain": 14.83, "avg_current_gain": 29.0, "total_inv_cr": 621.96}, {"id": "4805", "name": "ICICI PRUDENTIAL LIFE INSURANCE", "segment": "Mainboard", "_pg": 6, "n_issues": 14.0, "avg_listing_gain": 25.98, "avg_current_gain": 62.3, "total_inv_cr": 547.4}, {"id": "4803", "name": "HDFC LIFE INSURANCE", "segment": "Mainboard", "_pg": 7, "n_issues": 16.0, "avg_listing_gain": 19.97, "avg_current_gain": 64.15, "total_inv_cr": 543.62}, {"id": "17", "name": "HSBC MUTUAL FUND", "segment": "Mainboard", "_pg": 7, "n_issues": 20.0, "avg_listing_gain": 19.41, "avg_current_gain": 36.44, "total_inv_cr": 530.55}, {"id": "20", "name": "INVESCO MUTUAL FUND", "segment": "Mainboard", "_pg": 7, "n_issues": 15.0, "avg_listing_gain": 20.2, "avg_current_gain": 68.89, "total_inv_cr": 513.89}, {"id": "46", "name": "UTI MUTUAL FUND", "segment": "Mainboard", "_pg": 7, "n_issues": 14.0, "avg_listing_gain": 22.06, "avg_current_gain": 11.01, "total_inv_cr": 469.55}, {"id": "833", "name": "EASTSPRING", "segment": "Mainboard", "_pg": 8, "n_issues": 19.0, "avg_listing_gain": 21.78, "avg_current_gain": 64.35, "total_inv_cr": 402.19}, {"id": "4782", "name": "ADITYA BIRLA SUN LIFE INSURANCE", "segment": "Mainboard", "_pg": 8, "n_issues": 16.0, "avg_listing_gain": 12.68, "avg_current_gain": 23.52, "total_inv_cr": 379.84}, {"id": "9", "name": "BARODA BNP PARIBAS MUTUAL FUND", "segment": "Mainboard", "_pg": 8, "n_issues": 18.0, "avg_listing_gain": 11.2, "avg_current_gain": 20.91, "total_inv_cr": 377.09}, {"id": "2564", "name": "PRUDENTIAL", "segment": "Mainboard", "_pg": 8, "n_issues": 9.0, "avg_listing_gain": 6.96, "avg_current_gain": 70.07, "total_inv_cr": 353.77}, {"id": "4786", "name": "AXIS MAX LIFE INSURANCE", "segment": "Mainboard", "_pg": 9, "n_issues": 16.0, "avg_listing_gain": 19.09, "avg_current_gain": 38.99, "total_inv_cr": 335.19}, {"id": "1081", "name": "T.ROWE PRICE", "segment": "Mainboard", "_pg": 9, "n_issues": 3.0, "avg_listing_gain": 18.74, "avg_current_gain": 16.74, "total_inv_cr": 333.36}, {"id": "4827", "name": "SBI GENERAL INSURANCE", "segment": "Mainboard", "_pg": 9, "n_issues": 20.0, "avg_listing_gain": 9.24, "avg_current_gain": 37.42, "total_inv_cr": 329.77}, {"id": "3105", "name": "THINK INDIA", "segment": "Mainboard", "_pg": 9, "n_issues": 4.0, "avg_listing_gain": 15.99, "avg_current_gain": 83.87, "total_inv_cr": 328.07}, {"id": "714", "name": "TEMPLETON", "segment": "Mainboard", "_pg": 9, "n_issues": 6.0, "avg_listing_gain": 20.78, "avg_current_gain": 56.26, "total_inv_cr": 302.57}, {"id": "10", "name": "CANARA ROBECO MUTUAL FUND", "segment": "Mainboard", "_pg": 10, "n_issues": 11.0, "avg_listing_gain": 20.94, "avg_current_gain": 44.88, "total_inv_cr": 285.72}, {"id": "2482", "name": "PINEBRIDGE", "segment": "Mainboard", "_pg": 10, "n_issues": 15.0, "avg_listing_gain": 9.91, "avg_current_gain": 15.76, "total_inv_cr": 280.85}, {"id": "2141", "name": "MONETARY AUTHORITY OF SINGAPORE", "segment": "Mainboard", "_pg": 10, "n_issues": 10.0, "avg_listing_gain": 28.71, "avg_current_gain": 73.71, "total_inv_cr": 270.33}, {"id": "2002", "name": "SCHRODER", "segment": "Mainboard", "_pg": 10, "n_issues": 4.0, "avg_listing_gain": 30.7, "avg_current_gain": 22.99, "total_inv_cr": 269.22}, {"id": "1682", "name": "JP MORGAN", "segment": "Mainboard", "_pg": 10, "n_issues": 3.0, "avg_listing_gain": 9.14, "avg_current_gain": 19.62, "total_inv_cr": 267.34}, {"id": "518", "name": "BNP PARIBAS", "segment": "Mainboard", "_pg": 11, "n_issues": 22.0, "avg_listing_gain": 6.71, "avg_current_gain": 29.38, "total_inv_cr": 262.85}, {"id": "2325", "name": "NUVAMA", "segment": "Mainboard", "_pg": 11, "n_issues": 18.0, "avg_listing_gain": 9.33, "avg_current_gain": 0.58, "total_inv_cr": 256.17}, {"id": "3867", "name": "FRANKLIN TEMPLETON", "segment": "Mainboard", "_pg": 11, "n_issues": 7.0, "avg_listing_gain": 17.05, "avg_current_gain": 46.3, "total_inv_cr": 251.77}, {"id": "4904", "name": "SBI NPS TRUST", "segment": "Mainboard", "_pg": 11, "n_issues": 6.0, "avg_listing_gain": 22.7, "avg_current_gain": 34.31, "total_inv_cr": 251.75}, {"id": "2", "name": "360 ONE MUTUAL FUND", "segment": "Mainboard", "_pg": 11, "n_issues": 9.0, "avg_listing_gain": 10.67, "avg_current_gain": 21.34, "total_inv_cr": 237.26}, {"id": "222", "name": "ALLIANZ", "segment": "Mainboard", "_pg": 12, "n_issues": 9.0, "avg_listing_gain": 19.16, "avg_current_gain": 84.32, "total_inv_cr": 231.41}, {"id": "318", "name": "ARANDA INVESTMENTS", "segment": "Mainboard", "_pg": 12, "n_issues": 3.0, "avg_listing_gain": 24.2, "avg_current_gain": 96.5, "total_inv_cr": 228.21}, {"id": "199", "name": "AL MEHWAR COMMERCIAL INVESTMENTS LLC", "segment": "Mainboard", "_pg": 12, "n_issues": 10.0, "avg_listing_gain": 15.59, "avg_current_gain": 35.29, "total_inv_cr": 225.51}, {"id": "3528", "name": "ABAKKUS", "segment": "Mainboard", "_pg": 12, "n_issues": 13.0, "avg_listing_gain": 8.41, "avg_current_gain": 5.96, "total_inv_cr": 220.55}, {"id": "8544", "name": "BAJAJ LIFE INSURANCE", "segment": "Mainboard", "_pg": 12, "n_issues": 11.0, "avg_listing_gain": 12.7, "avg_current_gain": 17.41, "total_inv_cr": 213.99}, {"id": "2122", "name": "MIRAE", "segment": "Mainboard", "_pg": 13, "n_issues": 8.0, "avg_listing_gain": 22.71, "avg_current_gain": 22.71, "total_inv_cr": 209.17}, {"id": "4928", "name": "HDFC NPS TRUST", "segment": "Mainboard", "_pg": 13, "n_issues": 4.0, "avg_listing_gain": 17.33, "avg_current_gain": 32.25, "total_inv_cr": 204.75}, {"id": "532", "name": "BORDER TO COAST", "segment": "Mainboard", "_pg": 13, "n_issues": 3.0, "avg_listing_gain": 8.79, "avg_current_gain": 43.94, "total_inv_cr": 198.08}, {"id": "625", "name": "CAPITAL GROUP", "segment": "Mainboard", "_pg": 13, "n_issues": 3.0, "avg_listing_gain": 9.14, "avg_current_gain": 19.62, "total_inv_cr": 197.57}, {"id": "8", "name": "BANK OF INDIA MUTUAL FUND", "segment": "Mainboard", "_pg": 13, "n_issues": 11.0, "avg_listing_gain": 11.07, "avg_current_gain": 59.28, "total_inv_cr": 183.92}, {"id": "8522", "name": "KOTAK LIFE INSURANCE", "segment": "Mainboard", "_pg": 14, "n_issues": 14.0, "avg_listing_gain": 16.86, "avg_current_gain": 24.78, "total_inv_cr": 180.46}, {"id": "1848", "name": "LC PHAROS", "segment": "Mainboard", "_pg": 14, "n_issues": 17.0, "avg_listing_gain": -0.37, "avg_current_gain": 17.16, "total_inv_cr": 180.37}, {"id": "1388", "name": "GSS OPPORTUNITIES", "segment": "Mainboard", "_pg": 14, "n_issues": 1.0, "avg_listing_gain": 4.58, "avg_current_gain": -30.31, "total_inv_cr": 175.0}, {"id": "2476", "name": "PICTET", "segment": "Mainboard", "_pg": 14, "n_issues": 4.0, "avg_listing_gain": 28.57, "avg_current_gain": 31.54, "total_inv_cr": 174.43}, {"id": "35", "name": "QUANT MUTUAL FUND", "segment": "Mainboard", "_pg": 15, "n_issues": 8.0, "avg_listing_gain": 18.12, "avg_current_gain": 19.73, "total_inv_cr": 169.87}, {"id": "25", "name": "LIC MUTUAL FUND", "segment": "Mainboard", "_pg": 15, "n_issues": 10.0, "avg_listing_gain": 11.59, "avg_current_gain": 51.91, "total_inv_cr": 166.21}, {"id": "2602", "name": "PUBLIC SECTOR PENSION INVESTMENT BOARD", "segment": "Mainboard", "_pg": 15, "n_issues": 7.0, "avg_listing_gain": 19.49, "avg_current_gain": 19.88, "total_inv_cr": 159.23}, {"id": "26", "name": "MAHINDRA MANULIFE MUTUAL FUND", "segment": "Mainboard", "_pg": 15, "n_issues": 11.0, "avg_listing_gain": 20.9, "avg_current_gain": 34.64, "total_inv_cr": 156.16}, {"id": "1463", "name": "HSBC", "segment": "Mainboard", "_pg": 15, "n_issues": 7.0, "avg_listing_gain": 4.01, "avg_current_gain": 28.07, "total_inv_cr": 156.0}, {"id": "2847", "name": "WCM", "segment": "Mainboard", "_pg": 16, "n_issues": 2.0, "avg_listing_gain": 27.3, "avg_current_gain": 42.69, "total_inv_cr": 155.3}, {"id": "33", "name": "PGIM INDIA MUTUAL FUND", "segment": "Mainboard", "_pg": 16, "n_issues": 12.0, "avg_listing_gain": 19.55, "avg_current_gain": 27.09, "total_inv_cr": 155.23}, {"id": "3420", "name": "WF ASIAN", "segment": "Mainboard", "_pg": 16, "n_issues": 3.0, "avg_listing_gain": 28.23, "avg_current_gain": 64.88, "total_inv_cr": 154.99}, {"id": "2982", "name": "STEADVIEW CAPITAL", "segment": "Mainboard", "_pg": 16, "n_issues": 6.0, "avg_listing_gain": 27.9, "avg_current_gain": 51.64, "total_inv_cr": 154.8}, {"id": "897", "name": "DF INTERNATIONAL PARTNERS", "segment": "Mainboard", "_pg": 16, "n_issues": 3.0, "avg_listing_gain": 48.84, "avg_current_gain": 69.22, "total_inv_cr": 153.99}, {"id": "427", "name": "BAILLIE GIFFORD", "segment": "Mainboard", "_pg": 17, "n_issues": 2.0, "avg_listing_gain": 33.44, "avg_current_gain": 38.44, "total_inv_cr": 151.55}, {"id": "712", "name": "CITIGROUP", "segment": "Mainboard", "_pg": 17, "n_issues": 22.0, "avg_listing_gain": 9.04, "avg_current_gain": 5.59, "total_inv_cr": 146.18}, {"id": "1690", "name": "MANULIFE", "segment": "Mainboard", "_pg": 17, "n_issues": 8.0, "avg_listing_gain": 20.1, "avg_current_gain": 75.75, "total_inv_cr": 145.36}, {"id": "737", "name": "CLSA", "segment": "Mainboard", "_pg": 17, "n_issues": 5.0, "avg_listing_gain": 18.83, "avg_current_gain": 23.17, "total_inv_cr": 142.95}, {"id": "4790", "name": "BHARTI AXA LIFE INSURANCE", "segment": "Mainboard", "_pg": 18, "n_issues": 13.0, "avg_listing_gain": 19.39, "avg_current_gain": 44.75, "total_inv_cr": 141.82}, {"id": "2277", "name": "NIPPON", "segment": "Mainboard", "_pg": 18, "n_issues": 7.0, "avg_listing_gain": 7.95, "avg_current_gain": 18.24, "total_inv_cr": 137.0}, {"id": "1591", "name": "INQ HOLDING", "segment": "Mainboard", "_pg": 18, "n_issues": 1.0, "avg_listing_gain": 48.24, "avg_current_gain": 37.31, "total_inv_cr": 136.53}, {"id": "1991", "name": "MASSACHUSETTS INSTITUTE OF TECHNOLOGY", "segment": "Mainboard", "_pg": 18, "n_issues": 3.0, "avg_listing_gain": 20.51, "avg_current_gain": 59.12, "total_inv_cr": 134.98}, {"id": "1755", "name": "JUPITER", "segment": "Mainboard", "_pg": 18, "n_issues": 4.0, "avg_listing_gain": 17.04, "avg_current_gain": -8.21, "total_inv_cr": 134.17}, {"id": "1959", "name": "MALABAR", "segment": "Mainboard", "_pg": 19, "n_issues": 6.0, "avg_listing_gain": 13.77, "avg_current_gain": 42.59, "total_inv_cr": 133.84}, {"id": "21", "name": "ITI MUTUAL FUND", "segment": "Mainboard", "_pg": 19, "n_issues": 13.0, "avg_listing_gain": -0.63, "avg_current_gain": 44.65, "total_inv_cr": 132.54}, {"id": "1816", "name": "KOTAK", "segment": "Mainboard", "_pg": 19, "n_issues": 10.0, "avg_listing_gain": 7.73, "avg_current_gain": 59.0, "total_inv_cr": 130.25}, {"id": "107", "name": "ABERDEEN", "segment": "Mainboard", "_pg": 19, "n_issues": 2.0, "avg_listing_gain": 25.61, "avg_current_gain": 28.92, "total_inv_cr": 126.89}, {"id": "4909", "name": "VQ FASTERCAP", "segment": "Mainboard", "_pg": 20, "n_issues": 5.0, "avg_listing_gain": -1.0, "avg_current_gain": 1.72, "total_inv_cr": 125.69}, {"id": "8412", "name": "NEW WORLD FUND", "segment": "Mainboard", "_pg": 20, "n_issues": 1.0, "avg_listing_gain": 0.27, "avg_current_gain": 35.15, "total_inv_cr": 125.0}, {"id": "3495", "name": "ZULIA", "segment": "Mainboard", "_pg": 20, "n_issues": 1.0, "avg_listing_gain": 19.44, "avg_current_gain": 45.96, "total_inv_cr": 124.22}, {"id": "3141", "name": "TOCU EUROPE", "segment": "Mainboard", "_pg": 20, "n_issues": 11.0, "avg_listing_gain": 4.02, "avg_current_gain": 42.4, "total_inv_cr": 121.49}, {"id": "3129", "name": "TIMF HOLDINGS", "segment": "Mainboard", "_pg": 20, "n_issues": 3.0, "avg_listing_gain": 34.77, "avg_current_gain": 28.08, "total_inv_cr": 120.76}, {"id": "1196", "name": "FLORIDA RETIREMENT SYSTEM", "segment": "Mainboard", "_pg": 21, "n_issues": 8.0, "avg_listing_gain": 15.42, "avg_current_gain": 19.35, "total_inv_cr": 119.36}, {"id": "3512", "name": "3P INDIA", "segment": "Mainboard", "_pg": 21, "n_issues": 5.0, "avg_listing_gain": 10.16, "avg_current_gain": 35.16, "total_inv_cr": 116.54}, {"id": "388", "name": "ASTORNE CAPITAL", "segment": "Mainboard", "_pg": 21, "n_issues": 15.0, "avg_listing_gain": 8.52, "avg_current_gain": 19.92, "total_inv_cr": 115.43}, {"id": "1981", "name": "MARSHALL WACE", "segment": "Mainboard", "_pg": 22, "n_issues": 2.0, "avg_listing_gain": 3.24, "avg_current_gain": 23.42, "total_inv_cr": 113.02}, {"id": "23", "name": "JM FINANCIAL MUTUAL FUND", "segment": "Mainboard", "_pg": 22, "n_issues": 8.0, "avg_listing_gain": 6.42, "avg_current_gain": 14.96, "total_inv_cr": 112.96}, {"id": "40", "name": "SUNDARAM MUTUAL FUND", "segment": "Mainboard", "_pg": 22, "n_issues": 8.0, "avg_listing_gain": 24.67, "avg_current_gain": 27.29, "total_inv_cr": 109.57}, {"id": "4908", "name": "UTI NPS TRUST", "segment": "Mainboard", "_pg": 22, "n_issues": 3.0, "avg_listing_gain": 11.49, "avg_current_gain": 19.53, "total_inv_cr": 107.07}, {"id": "2158", "name": "MOTILAL OSWAL", "segment": "Mainboard", "_pg": 23, "n_issues": 4.0, "avg_listing_gain": 31.16, "avg_current_gain": 61.71, "total_inv_cr": 103.06}, {"id": "1917", "name": "LSPI", "segment": "Mainboard", "_pg": 23, "n_issues": 1.0, "avg_listing_gain": 0.13, "avg_current_gain": 15.23, "total_inv_cr": 100.0}, {"id": "4833", "name": "TATA AIA LIFE INSURANCE", "segment": "Mainboard", "_pg": 23, "n_issues": 7.0, "avg_listing_gain": 23.06, "avg_current_gain": 36.49, "total_inv_cr": 94.11}, {"id": "4907", "name": "TURNAROUND OPPORTUNITIES", "segment": "Mainboard", "_pg": 24, "n_issues": 4.0, "avg_listing_gain": -0.8, "avg_current_gain": 8.11, "total_inv_cr": 92.13}, {"id": "4905", "name": "SHAMYAK", "segment": "Mainboard", "_pg": 24, "n_issues": 4.0, "avg_listing_gain": 39.39, "avg_current_gain": 33.16, "total_inv_cr": 88.15}, {"id": "16", "name": "HELIOS MUTUAL FUND", "segment": "Mainboard", "_pg": 24, "n_issues": 7.0, "avg_listing_gain": 20.59, "avg_current_gain": 76.22, "total_inv_cr": 87.0}, {"id": "4386", "name": "SINGULARITY", "segment": "Mainboard", "_pg": 25, "n_issues": 6.0, "avg_listing_gain": 3.21, "avg_current_gain": -12.87, "total_inv_cr": 85.98}, {"id": "4796", "name": "EDELWEISS LIFE INSURANCE", "segment": "Mainboard", "_pg": 25, "n_issues": 13.0, "avg_listing_gain": 3.67, "avg_current_gain": 9.33, "total_inv_cr": 83.5}, {"id": "4823", "name": "RELIANCE GENERAL INSURANCE", "segment": "Mainboard", "_pg": 25, "n_issues": 9.0, "avg_listing_gain": 9.81, "avg_current_gain": 16.98, "total_inv_cr": 83.12}, {"id": "1598", "name": "INTEGRATED CORE", "segment": "Mainboard", "_pg": 25, "n_issues": 11.0, "avg_listing_gain": 9.34, "avg_current_gain": 18.45, "total_inv_cr": 82.67}, {"id": "635", "name": "CARMIGNAC", "segment": "Mainboard", "_pg": 26, "n_issues": 3.0, "avg_listing_gain": -2.73, "avg_current_gain": 4.95, "total_inv_cr": 82.64}, {"id": "521", "name": "MAYBANK", "segment": "Mainboard", "_pg": 26, "n_issues": 7.0, "avg_listing_gain": 8.62, "avg_current_gain": 51.59, "total_inv_cr": 80.5}, {"id": "4912", "name": "GAGANDEEP CREDIT CAPITAL", "segment": "Mainboard", "_pg": 26, "n_issues": 4.0, "avg_listing_gain": 1.79, "avg_current_gain": 32.81, "total_inv_cr": 78.99}, {"id": "2046", "name": "MATTHEWS", "segment": "Mainboard", "_pg": 26, "n_issues": 5.0, "avg_listing_gain": 11.09, "avg_current_gain": 33.04, "total_inv_cr": 77.99}, {"id": "362", "name": "ASHOKA", "segment": "Mainboard", "_pg": 26, "n_issues": 6.0, "avg_listing_gain": 20.5, "avg_current_gain": 24.56, "total_inv_cr": 77.87}, {"id": "4834", "name": "TATA AIG GENERAL INSURANCE", "segment": "Mainboard", "_pg": 27, "n_issues": 3.0, "avg_listing_gain": 18.75, "avg_current_gain": 8.72, "total_inv_cr": 76.86}, {"id": "3023", "name": "SUSQUEHANN", "segment": "Mainboard", "_pg": 27, "n_issues": 9.0, "avg_listing_gain": 18.11, "avg_current_gain": 34.2, "total_inv_cr": 76.26}, {"id": "45", "name": "UNION MUTUAL FUND", "segment": "Mainboard", "_pg": 27, "n_issues": 9.0, "avg_listing_gain": 21.27, "avg_current_gain": 43.4, "total_inv_cr": 75.96}, {"id": "2378", "name": "OPTIMIX", "segment": "Mainboard", "_pg": 27, "n_issues": 6.0, "avg_listing_gain": 12.78, "avg_current_gain": 6.6, "total_inv_cr": 75.01}, {"id": "237", "name": "ALPS/KOTAK INDIA", "segment": "Mainboard", "_pg": 28, "n_issues": 3.0, "avg_listing_gain": 14.45, "avg_current_gain": 26.85, "total_inv_cr": 70.88}, {"id": "2508", "name": "POLAR CAPITAL", "segment": "Mainboard", "_pg": 28, "n_issues": 2.0, "avg_listing_gain": 1.18, "avg_current_gain": 30.48, "total_inv_cr": 68.0}, {"id": "4791", "name": "CANARA HSBC", "segment": "Mainboard", "_pg": 28, "n_issues": 6.0, "avg_listing_gain": 13.89, "avg_current_gain": 24.72, "total_inv_cr": 64.75}, {"id": "2681", "name": "REGENTS OF THE UNIVERSITY OF CALIFORNIA", "segment": "Mainboard", "_pg": 29, "n_issues": 2.0, "avg_listing_gain": 17.78, "avg_current_gain": 53.5, "total_inv_cr": 62.42}, {"id": "2402", "name": "PACIFIC", "segment": "Mainboard", "_pg": 29, "n_issues": 3.0, "avg_listing_gain": 24.86, "avg_current_gain": 18.21, "total_inv_cr": 61.89}, {"id": "2770", "name": "SAMSUNG INDIA", "segment": "Mainboard", "_pg": 29, "n_issues": 4.0, "avg_listing_gain": 4.78, "avg_current_gain": -6.71, "total_inv_cr": 61.73}, {"id": "950", "name": "DSP", "segment": "Mainboard", "_pg": 30, "n_issues": 3.0, "avg_listing_gain": 24.12, "avg_current_gain": 17.65, "total_inv_cr": 61.36}, {"id": "42", "name": "TAURUS MUTUAL FUND", "segment": "Mainboard", "_pg": 30, "n_issues": 6.0, "avg_listing_gain": 5.08, "avg_current_gain": -6.11, "total_inv_cr": 60.04}, {"id": "6", "name": "BAJAJ FINSERV MUTUAL FUND", "segment": "Mainboard", "_pg": 30, "n_issues": 6.0, "avg_listing_gain": 22.15, "avg_current_gain": 126.92, "total_inv_cr": 58.3}, {"id": "3410", "name": "WELLINGTON", "segment": "Mainboard", "_pg": 30, "n_issues": 3.0, "avg_listing_gain": 34.67, "avg_current_gain": 75.13, "total_inv_cr": 57.34}, {"id": "4804", "name": "ICICI LOMBARD GENERAL INSURANCE", "segment": "Mainboard", "_pg": 31, "n_issues": 3.0, "avg_listing_gain": 24.04, "avg_current_gain": 10.36, "total_inv_cr": 55.0}, {"id": "4926", "name": "FSSA INDIAN SUBCONTINENT FUND", "segment": "Mainboard", "_pg": 31, "n_issues": 2.0, "avg_listing_gain": 44.33, "avg_current_gain": 83.3, "total_inv_cr": 54.98}, {"id": "1030", "name": "EMERGING MARKETS EQUITY", "segment": "Mainboard", "_pg": 31, "n_issues": 1.0, "avg_listing_gain": 0.27, "avg_current_gain": 35.15, "total_inv_cr": 54.34}, {"id": "1046", "name": "EMPLOYEES PROVIDENT FUND BOARD", "segment": "Mainboard", "_pg": 31, "n_issues": 3.0, "avg_listing_gain": 3.12, "avg_current_gain": 7.82, "total_inv_cr": 54.06}, {"id": "3645", "name": "AXIS", "segment": "Mainboard", "_pg": 31, "n_issues": 2.0, "avg_listing_gain": 2.07, "avg_current_gain": -7.11, "total_inv_cr": 53.65}, {"id": "4574", "name": "WHITEOAK", "segment": "Mainboard", "_pg": 32, "n_issues": 2.0, "avg_listing_gain": 10.8, "avg_current_gain": 31.35, "total_inv_cr": 51.25}, {"id": "3936", "name": "IKIGAI", "segment": "Mainboard", "_pg": 32, "n_issues": 5.0, "avg_listing_gain": 19.48, "avg_current_gain": 33.98, "total_inv_cr": 50.12}, {"id": "1237", "name": "FUNDPARTNER SOLUTIONS (SUISSE) SA", "segment": "Mainboard", "_pg": 33, "n_issues": 5.0, "avg_listing_gain": 24.65, "avg_current_gain": 21.78, "total_inv_cr": 48.43}, {"id": "751", "name": "COHESION MK", "segment": "Mainboard", "_pg": 33, "n_issues": 1.0, "avg_listing_gain": -2.99, "avg_current_gain": 13.02, "total_inv_cr": 48.0}, {"id": "1813", "name": "KORA", "segment": "Mainboard", "_pg": 33, "n_issues": 1.0, "avg_listing_gain": 53.23, "avg_current_gain": 74.82, "total_inv_cr": 48.0}, {"id": "2248", "name": "NEW HORIZON", "segment": "Mainboard", "_pg": 33, "n_issues": 1.0, "avg_listing_gain": -2.99, "avg_current_gain": 13.02, "total_inv_cr": 48.0}, {"id": "3073", "name": "TATA", "segment": "Mainboard", "_pg": 34, "n_issues": 5.0, "avg_listing_gain": 5.92, "avg_current_gain": 52.01, "total_inv_cr": 48.0}, {"id": "3123", "name": "TIGER GLOBAL", "segment": "Mainboard", "_pg": 34, "n_issues": 1.0, "avg_listing_gain": 53.23, "avg_current_gain": 74.82, "total_inv_cr": 48.0}, {"id": "2991", "name": "STICHTING", "segment": "Mainboard", "_pg": 34, "n_issues": 2.0, "avg_listing_gain": 6.5, "avg_current_gain": -1.98, "total_inv_cr": 46.35}, {"id": "1881", "name": "LION", "segment": "Mainboard", "_pg": 35, "n_issues": 6.0, "avg_listing_gain": 10.08, "avg_current_gain": 16.93, "total_inv_cr": 44.69}, {"id": "118", "name": "ABSL UMBRELLA UCITS FUND", "segment": "Mainboard", "_pg": 35, "n_issues": 5.0, "avg_listing_gain": 26.2, "avg_current_gain": 33.91, "total_inv_cr": 44.57}, {"id": "4510", "name": "UNIFI", "segment": "Mainboard", "_pg": 35, "n_issues": 3.0, "avg_listing_gain": 4.1, "avg_current_gain": 4.85, "total_inv_cr": 43.98}, {"id": "4903", "name": "SARASWATI COMMERCIAL", "segment": "Mainboard", "_pg": 36, "n_issues": 3.0, "avg_listing_gain": 30.97, "avg_current_gain": 151.25, "total_inv_cr": 43.0}, {"id": "3172", "name": "TREASURER OF THE STATE OF NORTH CAROLINA", "segment": "Mainboard", "_pg": 36, "n_issues": 1.0, "avg_listing_gain": 0.27, "avg_current_gain": 35.15, "total_inv_cr": 42.35}, {"id": "8496", "name": "SUPRIYATA CAPITAL", "segment": "Mainboard", "_pg": 37, "n_issues": 1.0, "avg_listing_gain": 19.44, "avg_current_gain": 45.96, "total_inv_cr": 40.0}, {"id": "8518", "name": "LSOI SPV", "segment": "Mainboard", "_pg": 37, "n_issues": 1.0, "avg_listing_gain": 0.27, "avg_current_gain": 35.15, "total_inv_cr": 40.0}, {"id": "113", "name": "ABRDN", "segment": "Mainboard", "_pg": 37, "n_issues": 1.0, "avg_listing_gain": 19.44, "avg_current_gain": 45.96, "total_inv_cr": 39.8}, {"id": "979", "name": "EAST BRIDGE", "segment": "Mainboard", "_pg": 37, "n_issues": 1.0, "avg_listing_gain": 13.64, "avg_current_gain": 2.07, "total_inv_cr": 37.0}, {"id": "1692", "name": "SBI", "segment": "Mainboard", "_pg": 38, "n_issues": 2.0, "avg_listing_gain": 22.48, "avg_current_gain": 53.33, "total_inv_cr": 37.0}, {"id": "2667", "name": "RBC", "segment": "Mainboard", "_pg": 38, "n_issues": 1.0, "avg_listing_gain": 13.64, "avg_current_gain": 2.07, "total_inv_cr": 37.0}, {"id": "3100", "name": "THELEME", "segment": "Mainboard", "_pg": 38, "n_issues": 1.0, "avg_listing_gain": 61.97, "avg_current_gain": 28.25, "total_inv_cr": 36.0}, {"id": "4894", "name": "CLARUS CAPITAL", "segment": "Mainboard", "_pg": 38, "n_issues": 3.0, "avg_listing_gain": 32.86, "avg_current_gain": 39.31, "total_inv_cr": 35.02}, {"id": "2546", "name": "PRINCIPAL", "segment": "Mainboard", "_pg": 38, "n_issues": 1.0, "avg_listing_gain": -0.63, "avg_current_gain": -6.02, "total_inv_cr": 35.0}, {"id": "3354", "name": "VIRIDIAN", "segment": "Mainboard", "_pg": 39, "n_issues": 6.0, "avg_listing_gain": 4.64, "avg_current_gain": 11.75, "total_inv_cr": 33.71}, {"id": "3691", "name": "BUOYANT", "segment": "Mainboard", "_pg": 39, "n_issues": 3.0, "avg_listing_gain": 15.68, "avg_current_gain": 65.19, "total_inv_cr": 33.28}, {"id": "8256", "name": "KIRAN VYPAR", "segment": "Mainboard", "_pg": 39, "n_issues": 2.0, "avg_listing_gain": 8.23, "avg_current_gain": 29.49, "total_inv_cr": 32.64}, {"id": "79", "name": "3PIM", "segment": "Mainboard", "_pg": 39, "n_issues": 3.0, "avg_listing_gain": 35.64, "avg_current_gain": 36.19, "total_inv_cr": 32.06}, {"id": "1734", "name": "JNL", "segment": "Mainboard", "_pg": 39, "n_issues": 2.0, "avg_listing_gain": 27.3, "avg_current_gain": 42.69, "total_inv_cr": 31.99}, {"id": "2256", "name": "NEW YORK STATE TEACHERS RETIREMENT SYSTEM", "segment": "Mainboard", "_pg": 40, "n_issues": 6.0, "avg_listing_gain": 15.03, "avg_current_gain": 30.03, "total_inv_cr": 31.91}, {"id": "8258", "name": "HCL CAPITAL", "segment": "Mainboard", "_pg": 40, "n_issues": 1.0, "avg_listing_gain": 1.38, "avg_current_gain": 10.57, "total_inv_cr": 30.88}, {"id": "4913", "name": "MAX LIFE INSURANCE", "segment": "Mainboard", "_pg": 40, "n_issues": 2.0, "avg_listing_gain": 38.44, "avg_current_gain": -5.65, "total_inv_cr": 30.75}, {"id": "2488", "name": "PIONEER", "segment": "Mainboard", "_pg": 40, "n_issues": 2.0, "avg_listing_gain": 28.83, "avg_current_gain": 113.77, "total_inv_cr": 30.48}, {"id": "4818", "name": "ORIENTAL INSURANCE", "segment": "Mainboard", "_pg": 41, "n_issues": 2.0, "avg_listing_gain": 9.19, "avg_current_gain": 8.45, "total_inv_cr": 30.0}, {"id": "2984", "name": "STEINBERG INDIA", "segment": "Mainboard", "_pg": 41, "n_issues": 4.0, "avg_listing_gain": 32.01, "avg_current_gain": 29.64, "total_inv_cr": 29.44}, {"id": "283", "name": "AMUNDSEN", "segment": "Mainboard", "_pg": 41, "n_issues": 3.0, "avg_listing_gain": 3.85, "avg_current_gain": -5.93, "total_inv_cr": 28.02}, {"id": "2315", "name": "NS PARTNERS", "segment": "Mainboard", "_pg": 41, "n_issues": 2.0, "avg_listing_gain": 4.54, "avg_current_gain": -5.84, "total_inv_cr": 28.01}, {"id": "264", "name": "AMERICAN FUNDS INSURANCE SERIES", "segment": "Mainboard", "_pg": 42, "n_issues": 2.0, "avg_listing_gain": 5.34, "avg_current_gain": -0.86, "total_inv_cr": 26.07}, {"id": "605", "name": "CAN LAH", "segment": "Mainboard", "_pg": 42, "n_issues": 2.0, "avg_listing_gain": 15.63, "avg_current_gain": 164.13, "total_inv_cr": 26.0}, {"id": "1469", "name": "HORNBILL ORCHID", "segment": "Mainboard", "_pg": 42, "n_issues": 1.0, "avg_listing_gain": 5.11, "avg_current_gain": -12.89, "total_inv_cr": 26.0}, {"id": "133", "name": "ACM", "segment": "Mainboard", "_pg": 43, "n_issues": 2.0, "avg_listing_gain": 29.42, "avg_current_gain": 43.59, "total_inv_cr": 25.81}, {"id": "8404", "name": "INDIA FUND", "segment": "Mainboard", "_pg": 43, "n_issues": 2.0, "avg_listing_gain": 33.84, "avg_current_gain": 41.64, "total_inv_cr": 25.44}, {"id": "1287", "name": "GHISALLO", "segment": "Mainboard", "_pg": 43, "n_issues": 4.0, "avg_listing_gain": 9.54, "avg_current_gain": 18.55, "total_inv_cr": 25.33}, {"id": "1781", "name": "KEDAARA", "segment": "Mainboard", "_pg": 43, "n_issues": 3.0, "avg_listing_gain": 18.81, "avg_current_gain": 152.39, "total_inv_cr": 25.12}, {"id": "3961", "name": "INDIA INFLECTION OPPORTUNITY", "segment": "Mainboard", "_pg": 44, "n_issues": 1.0, "avg_listing_gain": -8.73, "avg_current_gain": 185.71, "total_inv_cr": 25.0}, {"id": "4836", "name": "UNIVERSAL SOMPO GENERAL INSURANCE", "segment": "Mainboard", "_pg": 44, "n_issues": 5.0, "avg_listing_gain": 8.04, "avg_current_gain": 37.42, "total_inv_cr": 25.0}, {"id": "43", "name": "TRUST MUTUAL FUND", "segment": "Mainboard", "_pg": 44, "n_issues": 2.0, "avg_listing_gain": 20.34, "avg_current_gain": 59.78, "total_inv_cr": 24.33}, {"id": "345", "name": "AROHI", "segment": "Mainboard", "_pg": 44, "n_issues": 2.0, "avg_listing_gain": 57.6, "avg_current_gain": 51.54, "total_inv_cr": 23.13}, {"id": "4253", "name": "PI OPPORTUNITIES", "segment": "Mainboard", "_pg": 44, "n_issues": 1.0, "avg_listing_gain": -5.34, "avg_current_gain": -13.4, "total_inv_cr": 23.0}, {"id": "4530", "name": "VARANIUM", "segment": "Mainboard", "_pg": 45, "n_issues": 1.0, "avg_listing_gain": -7.83, "avg_current_gain": -40.23, "total_inv_cr": 21.9}, {"id": "2201", "name": "NATIONAL PENSION SERVICE", "segment": "Mainboard", "_pg": 45, "n_issues": 1.0, "avg_listing_gain": 13.64, "avg_current_gain": 2.07, "total_inv_cr": 20.92}, {"id": "1970", "name": "MAP INSTITUTIONAL", "segment": "Mainboard", "_pg": 45, "n_issues": 2.0, "avg_listing_gain": 57.6, "avg_current_gain": 51.54, "total_inv_cr": 20.87}, {"id": "1729", "name": "JF INDIA", "segment": "Mainboard", "_pg": 46, "n_issues": 3.0, "avg_listing_gain": 9.14, "avg_current_gain": 19.62, "total_inv_cr": 20.55}, {"id": "8257", "name": "NAVI FINSERV", "segment": "Mainboard", "_pg": 46, "n_issues": 1.0, "avg_listing_gain": 1.38, "avg_current_gain": 10.57, "total_inv_cr": 20.07}, {"id": "4824", "name": "RELIANCE NIPPON LIFE INSURANCE", "segment": "Mainboard", "_pg": 46, "n_issues": 2.0, "avg_listing_gain": 3.81, "avg_current_gain": -1.81, "total_inv_cr": 20.05}, {"id": "8543", "name": "BAJAJ GENERAL INSURANCE", "segment": "Mainboard", "_pg": 46, "n_issues": 3.0, "avg_listing_gain": 25.3, "avg_current_gain": 80.0, "total_inv_cr": 20.02}, {"id": "210", "name": "ALCHEMY", "segment": "Mainboard", "_pg": 47, "n_issues": 2.0, "avg_listing_gain": 1.4, "avg_current_gain": 56.89, "total_inv_cr": 20.0}, {"id": "980", "name": "EAST CAPITAL", "segment": "Mainboard", "_pg": 47, "n_issues": 1.0, "avg_listing_gain": 37.09, "avg_current_gain": 46.88, "total_inv_cr": 20.0}, {"id": "1829", "name": "KUWAIT INVESTMENT AUTHORITY", "segment": "Mainboard", "_pg": 47, "n_issues": 1.0, "avg_listing_gain": -0.63, "avg_current_gain": -6.02, "total_inv_cr": 20.0}, {"id": "3124", "name": "TIGER PACIFIC", "segment": "Mainboard", "_pg": 48, "n_issues": 1.0, "avg_listing_gain": -0.09, "avg_current_gain": 20.25, "total_inv_cr": 20.0}, {"id": "8494", "name": "DHARMAYUG INVESTMENTS", "segment": "Mainboard", "_pg": 49, "n_issues": 1.0, "avg_listing_gain": 19.44, "avg_current_gain": 45.96, "total_inv_cr": 20.0}, {"id": "8260", "name": "DEVELOPING COUNTRIES HIGH-QUALITY GROWTH EQUITY FUND", "segment": "Mainboard", "_pg": 49, "n_issues": 1.0, "avg_listing_gain": 1.38, "avg_current_gain": 10.57, "total_inv_cr": 19.09}, {"id": "4893", "name": "BONITAS", "segment": "Mainboard", "_pg": 49, "n_issues": 3.0, "avg_listing_gain": 38.37, "avg_current_gain": 38.06, "total_inv_cr": 18.27}, {"id": "1617", "name": "INTERNATIONAL RESEARCH EQUITY EXTENDED MASTER FUND (CAYMAN)", "segment": "Mainboard", "_pg": 50, "n_issues": 1.0, "avg_listing_gain": 53.23, "avg_current_gain": 74.82, "total_inv_cr": 17.53}, {"id": "4891", "name": "ARMY GROUP INSURANCE FUND,THE", "segment": "Mainboard", "_pg": 50, "n_issues": 2.0, "avg_listing_gain": 15.32, "avg_current_gain": 4.2, "total_inv_cr": 17.5}, {"id": "2003", "name": "UBS", "segment": "Mainboard", "_pg": 50, "n_issues": 1.0, "avg_listing_gain": -0.63, "avg_current_gain": -6.02, "total_inv_cr": 17.4}, {"id": "8517", "name": "EMERGING MARKETS EQUITIES FUND,INC.", "segment": "Mainboard", "_pg": 50, "n_issues": 1.0, "avg_listing_gain": 0.27, "avg_current_gain": 35.15, "total_inv_cr": 17.04}, {"id": "1439", "name": "HEREFORD", "segment": "Mainboard", "_pg": 50, "n_issues": 2.0, "avg_listing_gain": 15.56, "avg_current_gain": 26.48, "total_inv_cr": 17.0}, {"id": "4902", "name": "SAMEEKSHA INDIA EQUITY FUND", "segment": "Mainboard", "_pg": 51, "n_issues": 3.0, "avg_listing_gain": 9.46, "avg_current_gain": 66.72, "total_inv_cr": 16.54}, {"id": "1641", "name": "IPROFILE", "segment": "Mainboard", "_pg": 51, "n_issues": 3.0, "avg_listing_gain": 7.11, "avg_current_gain": 83.07, "total_inv_cr": 16.18}, {"id": "2333", "name": "OAKTREE", "segment": "Mainboard", "_pg": 51, "n_issues": 1.0, "avg_listing_gain": 13.64, "avg_current_gain": 2.07, "total_inv_cr": 16.08}, {"id": "4839", "name": "MNCL CAPITAL", "segment": "Mainboard", "_pg": 51, "n_issues": 1.0, "avg_listing_gain": 5.0, "avg_current_gain": 6.18, "total_inv_cr": 16.0}, {"id": "3292", "name": "VALIC CO.", "segment": "Mainboard", "_pg": 52, "n_issues": 1.0, "avg_listing_gain": 1.38, "avg_current_gain": 10.57, "total_inv_cr": 15.52}, {"id": "403", "name": "AURIGIN", "segment": "Mainboard", "_pg": 52, "n_issues": 3.0, "avg_listing_gain": -1.37, "avg_current_gain": 15.93, "total_inv_cr": 15.38}, {"id": "916", "name": "DISCOVERY GLOBAL", "segment": "Mainboard", "_pg": 52, "n_issues": 2.0, "avg_listing_gain": 3.54, "avg_current_gain": -14.13, "total_inv_cr": 15.31}, {"id": "1031", "name": "EMERGING MARKETS", "segment": "Mainboard", "_pg": 53, "n_issues": 1.0, "avg_listing_gain": 7.7, "avg_current_gain": -22.25, "total_inv_cr": 15.28}, {"id": "37", "name": "SAMCO MUTUAL FUND", "segment": "Mainboard", "_pg": 53, "n_issues": 1.0, "avg_listing_gain": -1.33, "avg_current_gain": -23.39, "total_inv_cr": 15.0}, {"id": "1845", "name": "LAZARD", "segment": "Mainboard", "_pg": 53, "n_issues": 1.0, "avg_listing_gain": 19.44, "avg_current_gain": 45.96, "total_inv_cr": 15.0}, {"id": "3522", "name": "AAA INDIA", "segment": "Mainboard", "_pg": 53, "n_issues": 2.0, "avg_listing_gain": 8.34, "avg_current_gain": -8.6, "total_inv_cr": 15.0}, {"id": "4892", "name": "BCAD", "segment": "Mainboard", "_pg": 54, "n_issues": 2.0, "avg_listing_gain": 4.15, "avg_current_gain": -5.67, "total_inv_cr": 15.0}, {"id": "4911", "name": "BHARAT VALUE", "segment": "Mainboard", "_pg": 54, "n_issues": 1.0, "avg_listing_gain": -8.73, "avg_current_gain": 185.71, "total_inv_cr": 15.0}, {"id": "894", "name": "DESTINATIONS", "segment": "Mainboard", "_pg": 54, "n_issues": 1.0, "avg_listing_gain": -5.34, "avg_current_gain": -13.4, "total_inv_cr": 14.99}, {"id": "2243", "name": "NEUBERGER BERMAN", "segment": "Mainboard", "_pg": 55, "n_issues": 1.0, "avg_listing_gain": -0.63, "avg_current_gain": -6.02, "total_inv_cr": 14.99}, {"id": "978", "name": "EAMC", "segment": "Mainboard", "_pg": 55, "n_issues": 1.0, "avg_listing_gain": 48.24, "avg_current_gain": 37.31, "total_inv_cr": 14.75}, {"id": "8524", "name": "NEF-PACIFIC EQUITY", "segment": "Mainboard", "_pg": 55, "n_issues": 2.0, "avg_listing_gain": 22.44, "avg_current_gain": 38.23, "total_inv_cr": 14.61}, {"id": "1673", "name": "JANUS HENDERSON", "segment": "Mainboard", "_pg": 55, "n_issues": 1.0, "avg_listing_gain": 53.23, "avg_current_gain": 74.82, "total_inv_cr": 13.87}, {"id": "2467", "name": "PGIM", "segment": "Mainboard", "_pg": 55, "n_issues": 2.0, "avg_listing_gain": 22.25, "avg_current_gain": 0.99, "total_inv_cr": 13.85}, {"id": "1625", "name": "INVESTERINGSFORENINGEN", "segment": "Mainboard", "_pg": 56, "n_issues": 1.0, "avg_listing_gain": 1.38, "avg_current_gain": 10.57, "total_inv_cr": 12.77}, {"id": "595", "name": "CALIFORNIA PUBLIC EMPLOYEES RETIREMENT SYSTEM", "segment": "Mainboard", "_pg": 56, "n_issues": 1.0, "avg_listing_gain": 0.27, "avg_current_gain": 35.15, "total_inv_cr": 12.7}, {"id": "4906", "name": "TROO CAPITAL", "segment": "Mainboard", "_pg": 56, "n_issues": 1.0, "avg_listing_gain": 1.85, "avg_current_gain": -33.15, "total_inv_cr": 12.64}, {"id": "421", "name": "AYUSHMAT", "segment": "Mainboard", "_pg": 57, "n_issues": 1.0, "avg_listing_gain": 4.58, "avg_current_gain": -30.31, "total_inv_cr": 12.0}, {"id": "4843", "name": "AUTHUM INVESTMENT", "segment": "Mainboard", "_pg": 57, "n_issues": 2.0, "avg_listing_gain": 30.16, "avg_current_gain": 42.6, "total_inv_cr": 12.0}, {"id": "8519", "name": "CONSTRUCTION & BUILDING UNIONS SUPERANNUATION FUND", "segment": "Mainboard", "_pg": 57, "n_issues": 1.0, "avg_listing_gain": 0.27, "avg_current_gain": 35.15, "total_inv_cr": 11.64}, {"id": "4895", "name": "EMERGE CAPITAL OPPORTUNITIES SCHEME", "segment": "Mainboard", "_pg": 58, "n_issues": 2.0, "avg_listing_gain": 7.82, "avg_current_gain": -1.96, "total_inv_cr": 11.37}, {"id": "2371", "name": "OP-INDIA", "segment": "Mainboard", "_pg": 58, "n_issues": 2.0, "avg_listing_gain": 3.99, "avg_current_gain": 6.45, "total_inv_cr": 11.25}, {"id": "4835", "name": "UNITED INDIA INSURANCE", "segment": "Mainboard", "_pg": 58, "n_issues": 2.0, "avg_listing_gain": 18.22, "avg_current_gain": 26.15, "total_inv_cr": 11.05}, {"id": "1319", "name": "GLOBAL RESEARCH EQUITY EXTENDED MASTER FUND (CAYMAN)", "segment": "Mainboard", "_pg": 58, "n_issues": 1.0, "avg_listing_gain": 19.44, "avg_current_gain": 45.96, "total_inv_cr": 10.93}, {"id": "3549", "name": "AIONIOS", "segment": "Mainboard", "_pg": 59, "n_issues": 1.0, "avg_listing_gain": 29.53, "avg_current_gain": 195.12, "total_inv_cr": 10.1}, {"id": "936", "name": "DOVETAIL", "segment": "Mainboard", "_pg": 59, "n_issues": 2.0, "avg_listing_gain": 14.24, "avg_current_gain": 2.8, "total_inv_cr": 10.06}, {"id": "4012", "name": "INSIGHTFUL", "segment": "Mainboard", "_pg": 59, "n_issues": 2.0, "avg_listing_gain": 8.8, "avg_current_gain": 4.76, "total_inv_cr": 10.06}, {"id": "4930", "name": "HIGH CONVICTION FUND-SERIES I", "segment": "Mainboard", "_pg": 60, "n_issues": 1.0, "avg_listing_gain": 12.95, "avg_current_gain": -4.77, "total_inv_cr": 10.01}, {"id": "114", "name": "ABS DIRECT EQUITY FUND LLC", "segment": "Mainboard", "_pg": 60, "n_issues": 1.0, "avg_listing_gain": 19.44, "avg_current_gain": 45.96, "total_inv_cr": 10.0}, {"id": "235", "name": "ALPHAMINE", "segment": "Mainboard", "_pg": 60, "n_issues": 2.0, "avg_listing_gain": 3.18, "avg_current_gain": -11.69, "total_inv_cr": 10.0}, {"id": "263", "name": "AMERICAN FUNDS", "segment": "Mainboard", "_pg": 61, "n_issues": 1.0, "avg_listing_gain": 7.7, "avg_current_gain": -22.25, "total_inv_cr": 10.0}, {"id": "346", "name": "ARP", "segment": "Mainboard", "_pg": 61, "n_issues": 1.0, "avg_listing_gain": 13.64, "avg_current_gain": 2.07, "total_inv_cr": 10.0}, {"id": "1294", "name": "GKFF VENTURES", "segment": "Mainboard", "_pg": 61, "n_issues": 1.0, "avg_listing_gain": 4.97, "avg_current_gain": -33.94, "total_inv_cr": 10.0}, {"id": "1622", "name": "INVESCO", "segment": "Mainboard", "_pg": 61, "n_issues": 1.0, "avg_listing_gain": 23.63, "avg_current_gain": 48.41, "total_inv_cr": 10.0}, {"id": "2226", "name": "NATIXIS", "segment": "Mainboard", "_pg": 62, "n_issues": 1.0, "avg_listing_gain": 28.63, "avg_current_gain": -48.61, "total_inv_cr": 10.0}, {"id": "2381", "name": "ORBIMED", "segment": "Mainboard", "_pg": 62, "n_issues": 1.0, "avg_listing_gain": -0.09, "avg_current_gain": 20.25, "total_inv_cr": 10.0}, {"id": "2396", "name": "OXBOW", "segment": "Mainboard", "_pg": 62, "n_issues": 2.0, "avg_listing_gain": 18.22, "avg_current_gain": 70.44, "total_inv_cr": 10.0}, {"id": "2925", "name": "SOLEL", "segment": "Mainboard", "_pg": 62, "n_issues": 1.0, "avg_listing_gain": 19.44, "avg_current_gain": 45.96, "total_inv_cr": 10.0}, {"id": "3013", "name": "SUNDARAM", "segment": "Mainboard", "_pg": 62, "n_issues": 2.0, "avg_listing_gain": 24.26, "avg_current_gain": -1.69, "total_inv_cr": 10.0}, {"id": "3558", "name": "ALCHEMIE VENTURE", "segment": "Mainboard", "_pg": 63, "n_issues": 2.0, "avg_listing_gain": -3.64, "avg_current_gain": 43.52, "total_inv_cr": 10.0}, {"id": "3598", "name": "ARGAN", "segment": "Mainboard", "_pg": 63, "n_issues": 1.0, "avg_listing_gain": 53.1, "avg_current_gain": 43.26, "total_inv_cr": 10.0}, {"id": "3701", "name": "CAPITAL 2B", "segment": "Mainboard", "_pg": 63, "n_issues": 1.0, "avg_listing_gain": -1.39, "avg_current_gain": -33.72, "total_inv_cr": 10.0}, {"id": "4266", "name": "PLUTUS", "segment": "Mainboard", "_pg": 63, "n_issues": 1.0, "avg_listing_gain": 12.05, "avg_current_gain": 39.3, "total_inv_cr": 10.0}, {"id": "4291", "name": "QUEST INVESTMENT", "segment": "Mainboard", "_pg": 64, "n_issues": 1.0, "avg_listing_gain": 1.38, "avg_current_gain": 10.57, "total_inv_cr": 10.0}, {"id": "4798", "name": "FUTURE GENERALI INDIA LIFE INSURANCE", "segment": "Mainboard", "_pg": 64, "n_issues": 2.0, "avg_listing_gain": 24.94, "avg_current_gain": 21.43, "total_inv_cr": 10.0}, {"id": "4897", "name": "GLOBE FINCAP", "segment": "Mainboard", "_pg": 65, "n_issues": 2.0, "avg_listing_gain": 9.19, "avg_current_gain": 8.45, "total_inv_cr": 10.0}, {"id": "4943", "name": "SUN LIFE ADITYA BIRLA INDIA FUND", "segment": "Mainboard", "_pg": 65, "n_issues": 1.0, "avg_listing_gain": 7.09, "avg_current_gain": 25.67, "total_inv_cr": 10.0}, {"id": "4008", "name": "INNOVEN CAPITAL", "segment": "Mainboard", "_pg": 66, "n_issues": 1.0, "avg_listing_gain": 5.11, "avg_current_gain": -12.89, "total_inv_cr": 9.96}, {"id": "1634", "name": "IOWA PUBLIC EMPLOYEE'S RETIREMENT SYSTEM", "segment": "Mainboard", "_pg": 66, "n_issues": 1.0, "avg_listing_gain": 0.27, "avg_current_gain": 35.15, "total_inv_cr": 9.94}, {"id": "412", "name": "AVIVA", "segment": "Mainboard", "_pg": 66, "n_issues": 1.0, "avg_listing_gain": 53.23, "avg_current_gain": 74.82, "total_inv_cr": 9.93}, {"id": "3310", "name": "VARIABLE INSURANCE PRODUCTS FUND", "segment": "Mainboard", "_pg": 66, "n_issues": 1.0, "avg_listing_gain": 0.27, "avg_current_gain": 35.15, "total_inv_cr": 9.19}, {"id": "2590", "name": "PUBLIC INSTITUTION FOR SOCIAL SECURITY", "segment": "Mainboard", "_pg": 67, "n_issues": 1.0, "avg_listing_gain": 1.38, "avg_current_gain": 10.57, "total_inv_cr": 8.55}, {"id": "1482", "name": "HUDSON BAY", "segment": "Mainboard", "_pg": 67, "n_issues": 1.0, "avg_listing_gain": 0.13, "avg_current_gain": 15.23, "total_inv_cr": 8.33}, {"id": "2069", "name": "MERCER", "segment": "Mainboard", "_pg": 67, "n_issues": 1.0, "avg_listing_gain": 1.38, "avg_current_gain": 10.57, "total_inv_cr": 7.71}, {"id": "1396", "name": "GUIDESTONE", "segment": "Mainboard", "_pg": 67, "n_issues": 1.0, "avg_listing_gain": 0.27, "avg_current_gain": 35.15, "total_inv_cr": 7.07}, {"id": "8259", "name": "EMPOWER EMERGING MARKETS EQUITY FUND", "segment": "Mainboard", "_pg": 68, "n_issues": 1.0, "avg_listing_gain": 1.38, "avg_current_gain": 10.57, "total_inv_cr": 6.63}, {"id": "1616", "name": "INTERNATIONAL OPPORTUNITY FUND", "segment": "Mainboard", "_pg": 68, "n_issues": 1.0, "avg_listing_gain": 1.38, "avg_current_gain": 10.57, "total_inv_cr": 6.52}, {"id": "8400", "name": "BEST INVESTMENT CORP.", "segment": "Mainboard", "_pg": 68, "n_issues": 1.0, "avg_listing_gain": 13.64, "avg_current_gain": 2.07, "total_inv_cr": 6.34}, {"id": "2772", "name": "SAN FRANCISCO CITY & COUNTY EMPLOYEES' RETIREMENT SYSTEM", "segment": "Mainboard", "_pg": 68, "n_issues": 1.0, "avg_listing_gain": 0.27, "avg_current_gain": 35.15, "total_inv_cr": 6.3}, {"id": "1362", "name": "GREATER INDIA", "segment": "Mainboard", "_pg": 69, "n_issues": 1.0, "avg_listing_gain": 31.33, "avg_current_gain": 104.6, "total_inv_cr": 5.7}, {"id": "2070", "name": "MERCURY", "segment": "Mainboard", "_pg": 69, "n_issues": 1.0, "avg_listing_gain": 28.13, "avg_current_gain": 32.42, "total_inv_cr": 5.68}, {"id": "4176", "name": "NEPEAN", "segment": "Mainboard", "_pg": 69, "n_issues": 1.0, "avg_listing_gain": -2.99, "avg_current_gain": 13.02, "total_inv_cr": 5.38}, {"id": "2640", "name": "QUBE MASTER", "segment": "Mainboard", "_pg": 69, "n_issues": 1.0, "avg_listing_gain": 7.7, "avg_current_gain": -22.25, "total_inv_cr": 5.32}, {"id": "2974", "name": "STATE OF MICHIGAN RETIREMENT SYSTEM", "segment": "Mainboard", "_pg": 70, "n_issues": 1.0, "avg_listing_gain": 1.38, "avg_current_gain": 10.57, "total_inv_cr": 5.24}, {"id": "3273", "name": "UNIVERSITY OF NOTRE DAME DU LAC", "segment": "Mainboard", "_pg": 70, "n_issues": 1.0, "avg_listing_gain": 29.53, "avg_current_gain": 195.12, "total_inv_cr": 5.1}, {"id": "377", "name": "ASIO FUND VCC", "segment": "Mainboard", "_pg": 70, "n_issues": 1.0, "avg_listing_gain": -35.12, "avg_current_gain": -48.47, "total_inv_cr": 5.07}, {"id": "3576", "name": "AMPERSAND", "segment": "Mainboard", "_pg": 70, "n_issues": 1.0, "avg_listing_gain": -8.58, "avg_current_gain": 67.94, "total_inv_cr": 5.05}, {"id": "4353", "name": "SC FOUNDERS", "segment": "Mainboard", "_pg": 71, "n_issues": 1.0, "avg_listing_gain": 0.27, "avg_current_gain": 35.15, "total_inv_cr": 5.02}, {"id": "4800", "name": "GO DIGIT GENERAL INSURANCE", "segment": "Mainboard", "_pg": 71, "n_issues": 1.0, "avg_listing_gain": 0.27, "avg_current_gain": 35.15, "total_inv_cr": 5.02}, {"id": "14", "name": "GROWW MUTUAL FUND", "segment": "Mainboard", "_pg": 71, "n_issues": 1.0, "avg_listing_gain": -8.03, "avg_current_gain": -24.85, "total_inv_cr": 5.01}, {"id": "4896", "name": "GENERAL INSURANCE CORP.OF INDIA", "segment": "Mainboard", "_pg": 71, "n_issues": 1.0, "avg_listing_gain": 17.0, "avg_current_gain": 6.33, "total_inv_cr": 5.01}, {"id": "244", "name": "ALTUS", "segment": "Mainboard", "_pg": 72, "n_issues": 1.0, "avg_listing_gain": 17.0, "avg_current_gain": 6.33, "total_inv_cr": 5.0}, {"id": "749", "name": "COEUS GLOBAL", "segment": "Mainboard", "_pg": 72, "n_issues": 1.0, "avg_listing_gain": 9.35, "avg_current_gain": 14.96, "total_inv_cr": 5.0}, {"id": "1347", "name": "GP EMERGING MARKETS STRATEGIES", "segment": "Mainboard", "_pg": 72, "n_issues": 1.0, "avg_listing_gain": 29.53, "avg_current_gain": 195.12, "total_inv_cr": 5.0}, {"id": "1564", "name": "INDIA OPPORTUNITIES", "segment": "Mainboard", "_pg": 72, "n_issues": 1.0, "avg_listing_gain": -0.63, "avg_current_gain": -6.02, "total_inv_cr": 5.0}, {"id": "1914", "name": "LOS ANGELES", "segment": "Mainboard", "_pg": 73, "n_issues": 1.0, "avg_listing_gain": 19.44, "avg_current_gain": 45.96, "total_inv_cr": 5.0}, {"id": "2829", "name": "SEI INSTITUTIONAL", "segment": "Mainboard", "_pg": 73, "n_issues": 1.0, "avg_listing_gain": 1.38, "avg_current_gain": 10.57, "total_inv_cr": 5.0}, {"id": "3332", "name": "VERITION", "segment": "Mainboard", "_pg": 73, "n_issues": 1.0, "avg_listing_gain": 31.33, "avg_current_gain": 104.6, "total_inv_cr": 5.0}, {"id": "3379", "name": "W-ASIA", "segment": "Mainboard", "_pg": 73, "n_issues": 1.0, "avg_listing_gain": 17.0, "avg_current_gain": 6.33, "total_inv_cr": 5.0}, {"id": "3757", "name": "CSIM INDIA", "segment": "Mainboard", "_pg": 74, "n_issues": 1.0, "avg_listing_gain": 22.01, "avg_current_gain": 100.73, "total_inv_cr": 5.0}, {"id": "4445", "name": "SVADHA CAPITAL", "segment": "Mainboard", "_pg": 74, "n_issues": 1.0, "avg_listing_gain": 7.09, "avg_current_gain": 25.67, "total_inv_cr": 5.0}, {"id": "4801", "name": "GO DIGIT LIFE INSURANCE", "segment": "Mainboard", "_pg": 74, "n_issues": 1.0, "avg_listing_gain": 19.44, "avg_current_gain": 45.96, "total_inv_cr": 5.0}, {"id": "4815", "name": "NAVI GENERAL INSURANCE", "segment": "Mainboard", "_pg": 75, "n_issues": 1.0, "avg_listing_gain": 1.38, "avg_current_gain": 10.57, "total_inv_cr": 5.0}, {"id": "4914", "name": "SHUBHKAM VENTURES", "segment": "Mainboard", "_pg": 75, "n_issues": 1.0, "avg_listing_gain": 53.1, "avg_current_gain": 43.26, "total_inv_cr": 5.0}]